[
  {
    "index": 0,
    "title": "跨性别男性- 维基百科，自由的百科全书",
    "link": "https://zh.wikipedia.org/zh-hans/%E8%B7%A8%E6%80%A7%E5%88%A5%E7%94%B7%E6%80%A7",
    "snippet": "进行性别转换的跨性别男性常被称为女跨男（英语：FTM或F2M）。 “变性人 ... 学术文献普遍表明，比起跨性别女性，跨性别男性被同性所吸引的情况要少见不少；也 ..."
  },
  {
    "index": 1,
    "title": "性别肯定手术(女跨男)",
    "link": "https://zh.wikipedia.org/zh-hans/%E6%80%A7%E5%88%AB%E8%82%AF%E5%AE%9A%E6%89%8B%E6%9C%AF_(%E5%A5%B3%E8%B7%A8%E7%94%B7)",
    "snippet": "针对跨性别男性或指派性别女性的跨性别非二元性别人士的性别肯定手术包括各种改变解剖特征的外科手术，以提供更适合跨性别男性的男性身份和功能的身体特征。"
  },
  {
    "index": 2,
    "title": "認識跨性別",
    "link": "https://transgender.taipei/%E8%AA%8D%E8%AD%98%E8%B7%A8%E6%80%A7%E5%88%A5/",
    "snippet": "跨性別男性（Trans Man / FTM）：指從女性跨越到男性，也可簡稱跨男。 · 跨性別女性（Trans Woman / MTF）：指從男性跨越到女性，也可簡稱跨女。 · 非二元性別（Non-binary）：指性別 ..."
  },
  {
    "index": 3,
    "title": "跨性别者C先生（中）：我不想不男不女",
    "link": "https://cn.nytimes.com/china/20170322/transgender-china-2/",
    "snippet": "Mar 22, 2017 — 在成长过程中，C先生一直努力去探索自己的性别身份。他尝试过变换发型，选择穿男性的衣服，也想尝试变性手术的途径。这样的探索，长久以来一直为他的人生 ..."
  },
  {
    "index": 4,
    "title": "关于跨性别的事实- 妙佑医疗国际",
    "link": "https://www.mayoclinic.org/zh-hans/healthy-lifestyle/adult-health/in-depth/transgender-facts/art-20266812",
    "snippet": "Apr 21, 2023 — 词语“跨性别者”和“多元性别者”涵盖一系列性别认同和性别表达。这些词语超出了这样一种观点，即所有人只能被归类为两种性别中的一种：女性或男性。"
  },
  {
    "index": 5,
    "title": "中国跨性别群体- 生存现状调查报告",
    "link": "https://cnlgbtdata.com/files/uploads/2019/03/2017_%E4%B8%AD%E5%9B%BD%E8%B7%A8%E6%80%A7%E5%88%AB%E7%BE%A4%E4%BD%93%E7%94%9F%E5%AD%98%E7%8E%B0%E7%8A%B6%E8%B0%83%E7%A0%94%E6%8A%A5%E5%91%8A-%E5%8F%AF%E8%A7%86%E5%8C%96.pdf",
    "snippet": "... 男/女二元划分的性别. 角色。包括：. • 跨性别男性（Transgender Man）. 指认同自己是男性的跨性别者，又称女跨男（FTM）。 • 跨性别男性. Q2.1=b/c & Q2.2=a. • 跨性别女性."
  },
  {
    "index": 6,
    "title": "你真的準備好了嗎？跨男HRT前一定要知道的7件事 - Attaboy",
    "link": "https://trans-attaboy.com/7-things-you-should-know-before-t/",
    "snippet": "Jan 3, 2021 — 睪固酮不是萬靈丹，它可以抑制／逆轉女性化特徵，發展出男性化的外表，但修行還是在個人，必須練習和適應，才可能帶來「接近理想」的結果。例如聲音的變化過程中 ..."
  },
  {
    "index": 7,
    "title": "跨性別基本知識",
    "link": "http://www.tehk.org.hk/trans101_tc.html",
    "snippet": "跨性别女性是出生時被分配為男性的女性。 這通常被稱為男跨女(MTF或M2F)。 跨性别女性可能會遇到性别焦慮或能過渡；這個過程通常 ..."
  },
  {
    "index": 8,
    "title": "FB完整版｜女跨男者親自分享變性手術心得！人造「老二」超威 ...",
    "link": "https://www.facebook.com/memediatw/videos/fb%E5%AE%8C%E6%95%B4%E7%89%88%E5%A5%B3%E8%B7%A8%E7%94%B7%E8%80%85%E8%A6%AA%E8%87%AA%E5%88%86%E4%BA%AB%E8%AE%8A%E6%80%A7%E6%89%8B%E8%A1%93%E5%BF%83%E5%BE%97%E4%BA%BA%E9%80%A0%E8%80%81%E4%BA%8C%E8%B6%85%E5%A8%81%E7%8C%9B%E9%95%B7%E5%BA%A6%E5%A4%A7%E5%85%AC%E9%96%8B/760385327944969/"
  },
  {
    "index": 9,
    "title": "跨性别者性别认同的法律承认",
    "link": "https://www.undp.org/sites/g/files/zskgke326/files/migration/asia_pacific_rbap/81e35c0bbe5b80d746519d11bb00d20cb33c8990b529c6664137bf2127ce73cd.pdf",
    "snippet": "在就业方面，虽然多部法律有禁止就业性别歧视的规定，但这些法律呈现出碎片化特征，没有明确. 保护跨性别者的平等就业权。多数跨性别者尤其是跨性别女性（男跨女）求职困难，一些 ..."
  },
  {
    "index": 10,
    "title": "跨性别身份案终极胜诉：重温香港跨男谢浩霖争取性别“正名” ...",
    "link": "https://www.bbc.com/zhongwen/simp/chinese-news-64327239",
    "snippet": "Feb 6, 2023 — 跨性别男性谢浩霖（Henry Tse）在2017年和另两名原诉申请司法复核，挑战香港入境事务处以“完成全套变性手术”才能变更身份证上性别的标准。"
  },
  {
    "index": 11,
    "title": "跨性别女性",
    "link": "https://baike.baidu.com/item/%E8%B7%A8%E6%80%A7%E5%88%AB%E5%A5%B3%E6%80%A7/16697826",
    "snippet": "跨性别女性(英语：Transwoman or Trans woman or Trans-woman)，或跨性别女人、跨性女、跨女，意旨男跨女(英语：MTF or M2F)出生时生理性别为男性；性别认同为女性，由男性 ..."
  },
  {
    "index": 12,
    "title": "香港罕有跨性別武術家許瑋楓專訪：「我男變女，喜歡女生",
    "link": "https://www.bbc.com/zhongwen/trad/chinese-news-54553312",
    "snippet": "Nov 13, 2020 — 香港罕有跨性別武術家許瑋楓專訪：「我男變女，喜歡女生，一點不柔弱」 ... 40歲的許瑋楓（Terry Hui，原名許偉峰）是香港一名跨性別女性（跨女），她在四年前完成 ..."
  },
  {
    "index": 13,
    "title": "香港跨男的性別正名之路：「我要堂堂正正地用男性的身份生活 ...",
    "link": "https://www.youtube.com/watch?v=wxJoaaC7me8"
  },
  {
    "index": 14,
    "title": "男跨女 - 明光社|",
    "link": "https://www.truth-light.org.hk/%E9%97%9C%E9%8D%B5%E5%AD%97/%E7%94%B7%E8%B7%A8%E5%A5%B3",
    "snippet": "與常識道別的性別政治. 加拿大癌症協會最近向LGBT的群體道歉，並且順應他們的要求，將子宮頸改稱為前洞，因為一些女跨男（即是原生性別是女性、沒有做過任何變性手術，但自認為 ..."
  },
  {
    "index": 15,
    "title": "在泰跨性男人与女变男不那么容易",
    "link": "https://rubikhealth.com/zh/articles/a-transman-the-transition-from-female-to-male-never-easy-in-thailand",
    "snippet": "在泰跨性男人与女变男不那么容易 · 必须年满20岁，如果未满20岁，则必须有父母的来信才能进行手术。 · 患者必须始终生活在与性别相反的社会中并成功生活了至少12个月 · 必须 ..."
  },
  {
    "index": 16,
    "title": "台灣法院判決通過第一例自我宣稱「女跨男」 - No Self ID Taiwan",
    "link": "https://noselfidtw.cc/post/court-approves-first-female-to-male-self-identification-in-taiwan/",
    "snippet": "Jul 19, 2024 — 翻譯來源 ... 這是台灣第二例自我宣稱的法定性別變更判決，也是台灣首例自我宣稱「女跨男」判決。 昨天(5 月30 日) 上午 ，臺北高等行政法院宣布，一名生理女性 ..."
  },
  {
    "index": 17,
    "title": "跨性别男性",
    "link": "https://baike.baidu.com/item/%E8%B7%A8%E6%80%A7%E5%88%AB%E7%94%B7%E6%80%A7/16697778",
    "snippet": "跨性别男性是指出生时生理性别为女性，但自我性别认同为男性的人群，有时也称为“女跨男”。"
  },
  {
    "index": 18,
    "title": "伴盟跨性別資訊平台: 認識跨性別",
    "link": "https://transgender.tapcpr.org/",
    "snippet": "... 跨性別男性、跨性別女性、以及非二元性別。 （1）跨性別男性（Transgender Man）：出生指定性別並非男性、但性別認同為男性者。為了讓外表更趨近於自己認同的男性形象，部分跨男 ..."
  },
  {
    "index": 19,
    "title": "什麼是跨性別？ - Attaboy",
    "link": "https://trans-attaboy.com/what-is-transgender/",
    "snippet": "Aug 25, 2020 — 跨性別者是一個統稱，是指性別認同(心理性別)與出生時的性別(生理性別)不符的人。性別認同是指一個人認同自己身為男性、女性或其他性別的心理意識。生理 ..."
  },
  {
    "index": 20,
    "title": "全台首例女跨男免術換證勝訴尼莫：終於能正大光明說我是 ...",
    "link": "https://tw.news.yahoo.com/%E5%85%A8%E5%8F%B0%E9%A6%96%E4%BE%8B%E5%A5%B3%E8%B7%A8%E7%94%B7%E5%85%8D%E8%A1%93%E6%8F%9B%E8%AD%89%E5%8B%9D%E8%A8%B4-%E5%B0%BC%E8%8E%AB-%E7%B5%82%E6%96%BC%E8%83%BD%E6%AD%A3%E5%A4%A7%E5%85%89%E6%98%8E%E8%AA%AA%E6%88%91%E6%98%AF%E7%94%B7%E7%94%9F%E4%BA%86-083455896.html",
    "snippet": "May 30, 2024 — 全台首例女跨男免術換證勝訴尼莫：終於能正大光明說我是男生了 ... 跨性別男性「尼莫」因身體因素，無法進行性腺器官摘除手術，向戶政事務所申請變更性別登記被 ..."
  },
  {
    "index": 21,
    "title": "台灣法院判決通過第一例自我宣稱「女跨男」 - No Self ID Taiwan",
    "link": "https://noselfidtw.cc/post/court-approves-first-female-to-male-self-identification-in-taiwan/",
    "snippet": "Jul 19, 2024 — 翻譯來源 ... 這是台灣第二例自我宣稱的法定性別變更判決，也是台灣首例自我宣稱「女跨男」判決。 昨天(5 月30 日) 上午 ，臺北高等行政法院宣布，一名生理女性 ..."
  },
  {
    "index": 22,
    "title": "他是女／男人嗎？：論安潔拉‧卡特《新夏娃的激情》及費雷斯《 ...",
    "link": "https://www.airitilibrary.com/Article/Detail/U0002-1507201811572200",
    "snippet": "by SC Chang · 2018 — ... 女性身體體現出男性形象並躲避異性戀暴力及同性戀的排他性，因此羞恥的跨性別經驗來探討自我性別認同的矛盾及重新建構跨性別的主體成為本章的重點。 總結以上對於安潔 ..."
  },
  {
    "index": 23,
    "title": "女跨男 - 明光社|",
    "link": "https://www.truth-light.org.hk/%E9%97%9C%E9%8D%B5%E5%AD%97/%E5%A5%B3%E8%B7%A8%E7%94%B7",
    "snippet": "加拿大癌症協會最近向LGBT的群體道歉，並且順應他們的要求，將子宮頸改稱為前洞，因為一些女跨男（即是原生性別是女性、沒有做過任何變性手術，但自認為男性的人士），以及 ..."
  },
  {
    "index": 24,
    "title": "性別重置手術（變性手術）-陰莖成形術 - 中國醫藥大學附設醫院",
    "link": "https://www.cmuh.cmu.edu.tw/NewsInfo/NewsArticle?no=7676",
    "snippet": "Dec 8, 2021 — 現今國內女變男變性手術的醫療常規，在手術前須有兩位精神科（身心科）醫師鑑定通過且經跨性別團隊會議審查，始得進行手術。由於手術是不可逆的， ..."
  },
  {
    "index": 25,
    "title": "要不要招跨性别男性，美国顶尖女子学院跟学生吵起来了",
    "link": "https://news.sina.cn/2023-03-15/detail-imykxpqx8094719.d.html",
    "snippet": "Mar 15, 2023 — 目前，该学院仍坚持“女子学院”的身份，虽然在2015年该校的招生政策更新，允许跨性别女性（“男跨女”）和出生时被指定为女性的非二元性别人士被考虑录取，但这符合 ..."
  },
  {
    "index": 26,
    "title": "性別不安",
    "link": "https://health99.hpa.gov.tw/media/public/pdf/21920.pdf",
    "snippet": "2008 年的《腦》期刊指出. 在另一個大腦深處的構造10：下視丘的「間質核」有. 相似的發現，意即生理男性與跨男在此部位的構造相. 似，而生理女性與跨女也相似。Swaab 發現不同 ..."
  },
  {
    "index": 27,
    "title": "性別變更 - LGBT資訊專區- 臺北市政府",
    "link": "https://lgbt.gov.taipei/cp.aspx?n=7141B7FAB560582E",
    "snippet": "性別變更 · 女性想變更性別為男性，應檢附文件為： 經二位精神科專科醫師評估鑑定之診斷書及合格醫療機構開具已摘除女性性器官，包括乳房、子宮、卵巢之手術完成診斷書。(依 ..."
  },
  {
    "index": 28,
    "title": "E10｜從女生跨性成為男人跨性別者小捷獻聲說故事",
    "link": "https://www.mirrormedia.mg/story/20191210cul501",
    "snippet": "Dec 15, 2019 — 還有看A片時，小捷會很強烈的把他自己想像成男性的身份，很深刻的希望自己是擁有陰莖那個角色。在男女交往上，他喜歡異性戀的女性，但是她們通常比較會被擁有 ..."
  },
  {
    "index": 29,
    "title": "亚太跨性别健康蓝图",
    "link": "https://www.undp.org/sites/g/files/zskgke326/files/migration/asia_pacific_rbap/06134fe5d74f2f84023c5de3ee99656ba412f33aa87d6a66c24e6a3da2f6de19.pdf",
    "snippet": "... 跨性别者参与这一过程。 方框4.1：跨性别病人登记表示例. 1. 您目前的性别认同是那种？（可以多选）. □ 男性. □ 女性. □ 跨性别女性/跨性别女人/男跨女. □ 跨性别男性/跨性别 ..."
  },
  {
    "index": 30,
    "title": "从男性变女性的变性手术",
    "link": "https://www.kamolhospital.com/zh/blog/691/sex-change-surgery-from-male-to-female",
    "snippet": "性别转换外科医生的目标是将男性生殖器改造成女性生殖器。在此过程中，外科医生必须考虑阴道的深度和功能，以便进行性交。 简而言之，他们的主要目标是解决跨性别女性 ..."
  },
  {
    "index": 31,
    "title": "【謝海盟番外篇】變性男女大不同",
    "link": "https://tw.news.yahoo.com/%E8%AC%9D%E6%B5%B7%E7%9B%9F%E7%95%AA%E5%A4%96%E7%AF%87-%E8%AE%8A%E6%80%A7%E7%94%B7%E5%A5%B3%E5%A4%A7%E4%B8%8D%E5%90%8C-092500366.html",
    "snippet": "Aug 8, 2017 — 「全球關於跨性別者人口比例的研究主要集中在歐洲國家，其中男跨女（MtF）在人口中的比例，大約介於在11,900至45,000分之一；女跨男（FtM）大約介於30,400至 ..."
  },
  {
    "index": 32,
    "title": "體育熱話｜跨性別泳手正面交鋒「男跨女」被「女跨男」擊敗",
    "link": "https://www.hk01.com/%E5%8D%B3%E6%99%82%E9%AB%94%E8%82%B2/723240/%E9%AB%94%E8%82%B2%E7%86%B1%E8%A9%B1-%E8%B7%A8%E6%80%A7%E5%88%A5%E6%B3%B3%E6%89%8B%E6%AD%A3%E9%9D%A2%E4%BA%A4%E9%8B%92-%E7%94%B7%E8%B7%A8%E5%A5%B3-%E8%A2%AB-%E5%A5%B3%E8%B7%A8%E7%94%B7-%E6%93%8A%E6%95%97",
    "snippet": "Jan 12, 2022 — 美國賓州大學一名跨性別游泳泳手Lia Thomas，上月在邀請賽女子組項目打破全國紀錄並奪3冠，但近日在一場大學泳賽中落敗，贏她的是另一位由女性變性為男性 ..."
  },
  {
    "index": 33,
    "title": "“男性”变“女性”，手术就结束或刚开始",
    "link": "https://www.rubikhealth.com/zh/articles/male-to-female-surgery-it-s-finished-or-it-s-just-beginning",
    "snippet": "但是女变男有点难，但不是不可能的，因为在泰国也有从女性到男性的性别重新分配手术。 今天，我们深了解从男性到女性 “跨性别男性” 的过渡。 仅仅进行变性手术可以帮助 ..."
  },
  {
    "index": 34,
    "title": "Yu hsi cheng | 關於我女變男（FTM跨性別）的問與答1. 甚麼樣 ...",
    "link": "https://www.instagram.com/aczheng/p/CpBDwjOvPlg/",
    "snippet": "同性婚姻法已經通過了，同性戀者已經不需要改變性別才能走入婚姻，除非你是天生認為靈魂裝錯身體，不然不要做任何不可逆的手術，因為身體就一個，沒辦法開刀變 ..."
  },
  {
    "index": 35,
    "title": "跨性別女孩的感情經歷",
    "link": "https://vocus.cc/article/62204c69fd89780001b768c0",
    "snippet": "Mar 12, 2022 — 在跨性別裡性取向跟性別認同其實是要分開來看的兩件事喔!!還是有很多種多元的樣貌! 例如常見的:男跨女的喜歡男生的異性戀、男跨女喜歡女生的同性戀女 ..."
  },
  {
    "index": 36,
    "title": "【男人想想】一位女跨男的自敘：我的「pass」之路",
    "link": "https://www.thinkingtaiwan.com/content/7989",
    "snippet": "Nov 28, 2019 — 跨性別者無可迴避的需要不同程度的醫療資源，而U是使用賀爾蒙療法改變自己的聲音、脂肪分布及臉型。女跨男在這方面相較男跨女幸運，因為賀爾蒙療法的成效是 ..."
  },
  {
    "index": 37,
    "title": "跨性别者的生存自白：身体器官不能决定我的性别",
    "link": "https://m.thepaper.cn/newsDetail_forward_2722855",
    "snippet": "Dec 16, 2018 — 他们生为男性或女性，. 却认为自己本应是另一种性别。 据估计，亚太地区有0.3%的人口是跨性别，. 中国大陆 ..."
  },
  {
    "index": 38,
    "title": "跨性別相關族群| 跨視界跨性別議題特展成大TO‧拉酷社",
    "link": "https://nckulgbtclub.wixsite.com/website/%E8%B7%A8%E6%80%A7%E5%88%A5%E7%9B%B8%E9%97%9C%E6%97%8F%E7%BE%A4",
    "snippet": "男跨女、 女跨男. ​男跨女（簡稱跨女）. (Male to Female，MtF). 男跨女者為生理性別為男性. 但性別認同為女性的人. ​女跨男（簡稱跨男）. (Female to Male，FtM). 女跨男者為 ..."
  },
  {
    "index": 39,
    "title": "性別的多樣性- 伴盟跨性別資訊平台 - 台灣伴侶權益推動聯盟",
    "link": "https://transgender.tapcpr.org/what-is-gender",
    "snippet": "（四）性別認同（Gender Identity）：指個人依據自身身體與社會的性別經驗，發展出對於自身性別的認定，如男、女或非二元性別等。 （五）性傾向（Sexual Orientation）：指感受浪漫愛或 ..."
  },
  {
    "index": 40,
    "title": "多元性別LGBTQI - NUU 國立聯合大學性別平等教育委員會",
    "link": "https://gee.nuu.edu.tw/p/412-1026-5696.php",
    "snippet": "L=女同志(Lesbian). 也有人說「女同性戀」、「蕾絲邊」、「拉子」、「拉拉」等，指的是喜愛同性的女性。 · G=男同志(Gay) · B=雙性戀(Bisexual) · T=跨性別(Transgender) · 變性 ..."
  },
  {
    "index": 41,
    "title": "首例女性跨男性免術換證案勝訴伴侶盟籲勿上訴",
    "link": "https://www.cna.com.tw/news/ahel/202405300177.aspx",
    "snippet": "May 30, 2024 — 跨性別男性尼莫在未摘除性腺器官下要求變更性別登記遭拒提出訴訟，台北高等行政法院宣判尼莫勝訴，伴侶盟今天呼籲戶政事務所尊重判決不再上訴， ..."
  },
  {
    "index": 42,
    "title": "「跨粉」一個與跨性別有莫大相關，卻被遺忘了的身份",
    "link": "https://tgr.org.hk/index.php/zh/10-database/8-2016-10-16-17-54-04",
    "snippet": "Jan 10, 2017 — 而同性戀的女性喜歡上跨性別的男性，很多時候都是從女同志關系開始。跨性別的一方起初可能認同為女同性戀中的T ，又或者還在性別身份掙扎中，又或 ..."
  },
  {
    "index": 43,
    "title": "變更法定性別鬆綁Q&A",
    "link": "https://www.istscare.org/qna/",
    "snippet": "兵役與逃兵 · 一、 法定性別女性變更為男性者，未達除役年齡者，會收到兵役體檢通知，若是身體無法自然分泌男性荷爾蒙者，為「免役體位」。 · 二、 逾徵兵年齡男跨女跨性別者而 ..."
  },
  {
    "index": 44,
    "title": "異性同性都交往過女跨男變性成「超MAN大叔」吐最感動一刻",
    "link": "https://www.ctwant.com/article/173239/",
    "snippet": "Mar 17, 2022 — 網紅小A辣過去是跨性別者，為了讓自己更有女人味，自2018年起陸續動了不少整形手術，2020年10月更是前往泰國，進行性別重置手術，花費大約45萬台幣「送走 ..."
  },
  {
    "index": 45,
    "title": "跨性別人士- 女跨男｜FTM心路歷程｜回應網民大眾誤解｜喜歡 ...",
    "link": "https://www.facebook.com/whizoolab/videos/%E8%B7%A8%E6%80%A7%E5%88%A5%E4%BA%BA%E5%A3%AB-%E5%A5%B3%E8%B7%A8%E7%94%B7ftm%E5%BF%83%E8%B7%AF%E6%AD%B7%E7%A8%8B%E5%9B%9E%E6%87%89%E7%B6%B2%E6%B0%91%E5%A4%A7%E7%9C%BE%E8%AA%A4%E8%A7%A3%E5%96%9C%E6%AD%A1%E7%94%B7%E6%88%96%E5%A5%B3%E8%B7%A8%E7%94%B7%E5%8F%AF%E4%BB%A5%E7%94%9F%E5%B0%8F%E5%AD%A9-%E7%99%BD%E6%88%BF%E7%B4%99%E4%B8%8A%E8%AB%87/5465679070145183/"
  },
  {
    "index": 46,
    "title": "Nature | 女跨男性别确认睾酮治疗过程中的免疫适应",
    "link": "https://bydrug.pharmcube.com/news/detail/b72bad79d0627d244bcdb0cd5e3ab68d",
    "snippet": "ByDrug医药新闻摘要⌋ 2024-09-07 08:18，BioArt：传染性、炎症性和自身免疫性疾病在男性和女性中的表现不同。 比如初次感染SARS-CoV-2的男性的死亡风险相对略高， ..."
  },
  {
    "index": 47,
    "title": "第三章認識跨性別者（T）及其處境",
    "link": "https://www.boca.gov.tw/dl-2331-7e983e47d7e043f3b9c6d19c66e9d68a.html",
    "snippet": "從原本法律認定性別男性轉變為女性的變性者稱為MtF（Male to Female），. 也稱跨性別女性（transgender female）；原本女性轉變為男性的變性者稱為. FtM（Female to Male），也稱跨 ..."
  },
  {
    "index": 48,
    "title": "跨越性別的高牆系列報導（三）：性別改造術二—手術和陽具",
    "link": "https://medium.com/@alice820304/%E8%B7%A8%E8%B6%8A%E6%80%A7%E5%88%A5%E7%9A%84%E9%AB%98%E7%89%86%E7%B3%BB%E5%88%97%E5%A0%B1%E5%B0%8E-%E4%B8%89-%E6%80%A7%E5%88%A5%E6%94%B9%E9%80%A0%E8%A1%93%E4%BA%8C-%E6%89%8B%E8%A1%93%E5%92%8C%E9%99%BD%E5%85%B7-%E5%AD%90%E5%AE%AE%E5%B4%87%E6%8B%9C-8680967e67ea",
    "snippet": "小羿是生理女，這天他要進行的是女跨男性別還原手術中的第二階段— — 陰莖重建。在這之前，他幾乎每半年進一次手術房，分別做完胸部摘除、卵巢及子宮摘除，與埋 ..."
  },
  {
    "index": 49,
    "title": "女跨男-哔哩哔哩",
    "link": "https://m.bilibili.com/search?keyword=%E5%A5%B3%E8%B7%A8%E7%94%B7",
    "snippet": "bilibili为您提供女跨男相关的视频、番剧、影视、动画等内容。bilibili是国内知名的在线视频弹幕网站，拥有最棒的ACG氛围，哔哩哔哩内容丰富多元，涵盖动漫、电影、二次元 ..."
  },
  {
    "index": 50,
    "title": "是她、他，还是Gender X？一张证明不到跨性别人士身分的 ...",
    "link": "https://theinitium.com/zh-hans/article/20230324-hongkong-transgender-non-binary-and-their-hkid-card",
    "snippet": "Mar 23, 2023 — 她直言，那次经验，自己比较幸运，因为曾听闻有跨女被男警搜身，又被指骂“当男人好端端的，扮甚么女人”。 而恩恩一次到急症室看症，护士对着她的身分证，大叫她的 ..."
  },
  {
    "index": 51,
    "title": "跨性别男性（女跨男）讲述Bottom Surgery的经历‼️",
    "link": "https://www.reddit.com/r/weibo_read/comments/161i3og/%E8%B7%A8%E6%80%A7%E5%88%AB%E7%94%B7%E6%80%A7%E5%A5%B3%E8%B7%A8%E7%94%B7%E8%AE%B2%E8%BF%B0bottom_surgery%E7%9A%84%E7%BB%8F%E5%8E%86/",
    "snippet": "Be the first to comment. Nobody's responded to this post yet. Add your thoughts and get the conversation going."
  },
  {
    "index": 52,
    "title": "香港已完成手術跨男改身份證性別遭暫緩入境處：盡快處理",
    "link": "https://zh.wikinews.org/wiki/%E9%A6%99%E6%B8%AF%E5%B7%B2%E5%AE%8C%E6%88%90%E6%89%8B%E8%A1%93%E8%B7%A8%E7%94%B7%E6%94%B9%E8%BA%AB%E4%BB%BD%E8%AD%89%E6%80%A7%E5%88%A5%E9%81%AD%E6%9A%AB%E7%B7%A9_%E5%85%A5%E5%A2%83%E8%99%95%EF%BC%9A%E7%9B%A1%E5%BF%AB%E8%99%95%E7%90%86",
    "snippet": "這項承諾是在傳媒和性別友善組織的壓力下做出的，他們一再跟進一位聾人跨男的案例，該聾人去年完成了性別重置手術，但在申請更改身份證性別時遭到了阻礙。 海仔是一位女跨男的 ..."
  },
  {
    "index": 53,
    "title": "香港男跨女跨性別人士愛滋病風險及流行情況調查2017",
    "link": "https://www.aids.gov.hk/english/surveillance/sur_report/prism2017_tgc.pdf",
    "snippet": "背景. 男跨女跨性別人士（跨性別女性）一直是被忽視和難以接觸的社群，但各種海外研究表明，他們. 的愛滋病毒流行率可能很高。 為了更準確研究香港的情況，衞生署特別預防 ..."
  },
  {
    "index": 54,
    "title": "這些男跨女以為能分到一個拉子",
    "link": "https://noselfidtw.cc/post/these-men-were-promised-lesbians/",
    "snippet": "Dec 18, 2023 — 為什麼這麼多女孩正決定他們寧可當個男孩？【漫畫】 · 知名男同交友軟體為挺跨而全面禁搜「生理男性」，使用者一片哀鴻遍野，資深同運領袖也大力抨擊"
  },
  {
    "index": 55,
    "title": "美国举办跨性别冰球比赛，“女跨男”球员遭“男跨女”球员撞成 ...",
    "link": "https://www.sohu.com/a/617146773_115479",
    "snippet": "Dec 14, 2022 — （观察者网讯）据英国《每日邮报》12月13日报道，近日，美国威斯康星州米德尔顿举行了跨性别冰球比赛，期间，一名“男跨女”的跨性别球员将一名“女跨男”的球员 ..."
  },
  {
    "index": 56,
    "title": "面向世界，展示真我：跨性別系列之十六：Damien (女跨男) 的 ...",
    "link": "https://gdottv.com/main/archives/14492",
    "snippet": "這幾年間，會慢慢地探討各種不同建造人工陽具的手術方法。下一步便是和某些跨性別男士一樣，可以堂堂正正地進入男廁，站著對著尿盆小便。 攝製跨性別系列，是香港跨卓頻道創辦 ..."
  },
  {
    "index": 57,
    "title": "Search \"男跨女\"",
    "link": "https://www.plurk.com/search?q=%E7%94%B7%E8%B7%A8%E5%A5%B3",
    "snippet": "顯然吳宇萱要保留陰莖，只是為了生自己的小孩時，得以插入他所謂「分娩女」的陰道。 用男人的身體搶奪女人的權利，還不用負擔女人該付出的代價。打著性別平權的男人，卻自稱 ..."
  },
  {
    "index": 58,
    "title": "手術資訊／Surgery Information",
    "link": "https://genderempowerment.org/index.php/surgery-infomation/",
    "snippet": "跨性別女性(男跨女)有可能需要的手術. 性別肯定手術(Gender Affirming Surgery, GAS) (舊稱: 性別重置手術, SRS) ．陰莖包皮瓣手術(現時香港採用的主要手法) ．結腸法"
  },
  {
    "index": 59,
    "title": "紐約禁性別歧視納入跨性別者 - 國立清華大學性別平等教育委員會",
    "link": "https://gencom.site.nthu.edu.tw/p/16-1344-97604.php?Lang=zh-tw",
    "snippet": "... 跨性別男性（女跨男）與跨性別女性（男跨女）可分別進入自身認同的男用或女用公廁，跨性別員工「約翰（John）」識別證的名字也應寫上當事人想要的「珍（Jane ..."
  },
  {
    "index": 60,
    "title": "跨性別、LGBTQ+？人的「性別認同」到底可以多「多元」？",
    "link": "https://www.gq.com.tw/bettermen/article/%E6%80%A7%E5%88%A5%E8%AA%8D%E5%90%8C-%E6%80%A7%E5%88%A5%E5%B9%B3%E6%AC%8A-lgbtq",
    "snippet": "Jun 24, 2024 — 談論多元性別的時候很常討論到「LGBT」，然而這個英文縮寫是由「女同性戀者Lesbian」、「男同性戀者Gay」、「雙性戀者Bisexual」與「跨性別者Transgender」 ..."
  },
  {
    "index": 61,
    "title": "Vol.4|跨越性别：作为女性被养育十八年后，我终于站在了男人 ...",
    "link": "https://www.xiaoyuzhoufm.com/episode/64fd7574e490c5dee5d433a2",
    "snippet": "Sep 10, 2023 — 缩大是我们身边的一名跨性别男性朋友，三周前来北京进行了女跨男性别重置手术，也促成了我们在东郊的这次相聚。 两次的会面交流中，他分享了他的成长 ..."
  },
  {
    "index": 62,
    "title": "跨性别人群生存困境调查：多数人有遭受校园暴力经历 - 江西",
    "link": "http://jx.people.com.cn/n2/2020/0222/c186330-33818908.html",
    "snippet": "Feb 22, 2020 — 跨性别者通常是指一个人在心理上无法认同自己与生俱来的生理性别，相信自己应该属于另一种性别，主要包括跨性别男性、跨性别女性和性别酷儿跨性别人群所 ..."
  },
  {
    "index": 63,
    "title": "女跨男但喜歡男生的也有不是全部跨性別都算異性戀唷",
    "link": "https://www.threads.net/@axsonwannakaikai/post/C6CATg9Payx",
    "snippet": "Apr 21, 2024 — 延續變裝皇后話題 · 和友人討論她說：同志和跨性別（男變女或女變男）不ㄧ樣啊，跨性別者是算是異性戀，因為她內心認定自己不是生理上的性別，基本上是喜歡異性的 ..."
  },
  {
    "index": 64,
    "title": "從天菜成為「菜渣」，他們如何長成一個跨性別？",
    "link": "https://www.thenewslens.com/article/186676",
    "snippet": "Aug 14, 2023 — 泰瑞雖然生為女孩，但從小就一直覺得自己是男生。由於喜歡女孩，他曾經以為自己是個T，也就是比較陽剛的女同志，又隱隱約約覺得自己跟其它女同志朋友 ..."
  },
  {
    "index": 65,
    "title": "女性跨性别男性",
    "link": "https://www.douyin.com/search/%E5%A5%B3%E6%80%A7%E8%B7%A8%E6%80%A7%E5%88%AB%E7%94%B7%E6%80%A7",
    "snippet": "Oct 10, 2024 — 跨性别女性是指出生分配性别为男性、性别认同为女性，又称为男跨女。英文的跨性别最初是由美国的维吉妮亚·普林斯在1970年代创造的，用来和Transsexual（变性 ..."
  },
  {
    "index": 66,
    "title": "跨性別Transgender",
    "link": "https://www.youtube.com/playlist?list=PL2C9OZ3Lwi3FGq4zJDLuNlyOTBUcnRAiN",
    "snippet": "【微電影】《跨女心事》 - To 套or not to 套? (完整版-重新剪輯). Transgender ... 「跨兒故事」- 五位跨性別男性及一位母親的故事. Transgender Resource Center ..."
  },
  {
    "index": 67,
    "title": "國內女跨男變更性別訴訟首勝尼莫超開心：憑什麼一定要手術",
    "link": "https://www.ettoday.net/news/20240530/2749071.htm",
    "snippet": "May 30, 2024 — 出生為女性、始終自認為男生的跨性別男「尼莫」，訴請北市信義區戶政事務所變更他的性別登記為男性，台北高等行政法院今（30日）判「尼莫」勝訴， ..."
  },
  {
    "index": 68,
    "title": "跨性別人士被拒更改身份證性別案終院上訴得直- RTHK - 香港電台",
    "link": "https://news.rthk.hk/rthk/ch/component/k2/1686750-20230206.htm",
    "snippet": "Feb 6, 2023 — 未完成變性手術的跨性別人士被入境處拒絕更改身分證性別的案件，終審法院裁定政府敗訴，並宣告涉案政策規定女跨男的跨性別人士必須接受整個性別重置手術 ..."
  },
  {
    "index": 69,
    "title": "跨性別及性別不安－從臨床照護到心理壓力觀點",
    "link": "https://www.airitilibrary.com/Article/Detail/0047262x-N202301130019-00004",
    "snippet": "by HSU Chih-Yun · 2023 — ... ，非傳統性別認同的個體常遭到污名與霸凌，導致精神疾病的風險。跨 ... 女跨男或男跨女的個案在社會性別轉變的歷程中，也可能會尋求荷爾蒙治療或性別確認 ..."
  },
  {
    "index": 70,
    "title": "帥到美到超越性別! 9位你必追的性別重置IG名人",
    "link": "https://www.harpersbazaar.com/tw/fashion/fashionmodels/g26980625/8-transgender-models/",
    "snippet": "Jan 16, 2020 — ... 男變女、或女變男、這8位IG名人放下過去、擁抱新生。 讓 ... 的「跨跨性別」愛情故事. 廣告- 內文未完請往下捲動. Hair, Face, Head ..."
  },
  {
    "index": 71,
    "title": "以愛之名擁抱多元性別",
    "link": "https://www.tax.taichung.gov.tw/media/767964/1100903-cedaw%E9%80%B2%E9%9A%8E%E8%AA%B2%E7%A8%8B-%E5%A4%9A%E5%85%83%E6%80%A7%E5%88%A5%E6%AC%8A%E7%9B%8A%E7%B0%A1%E5%A0%B1.pdf",
    "snippet": "Jun 22, 2021 — 跨性別(transgender)、變性慾者. (transsexual)TS、女跨男(female to male, FtM)、男跨女(male to female, MtF)、變裝者(cross-."
  },
  {
    "index": 72,
    "title": "美醫誌-Memedia - FB完整版｜女跨男者親自分享變性手術 ...",
    "link": "https://www.facebook.com/memediatw/posts/fb%E5%AE%8C%E6%95%B4%E7%89%88%E5%A5%B3%E8%B7%A8%E7%94%B7%E8%80%85%E8%A6%AA%E8%87%AA%E5%88%86%E4%BA%AB%E8%AE%8A%E6%80%A7%E6%89%8B%E8%A1%93%E5%BF%83%E5%BE%97%E4%BA%BA%E9%80%A0%E8%80%81%E4%BA%8C%E8%B6%85%E5%A8%81%E7%8C%9B%E9%95%B7%E5%BA%A6%E5%A4%A7%E5%85%AC%E9%96%8B-%E4%BD%A0%E7%9F%A5%E9%81%93%E5%A5%B3%E8%B7%A8%E7%94%B7%E9%9C%80%E8%A6%81%E7%B6%93%E6%AD%B7%E5%93%AA%E4%BA%9B%E6%89%8B%E8%A1%93%E5%97%8E%E4%BA%BA%E5%B7%A5%E9%99%B0%E8%8E%96%E7%9A%84%E9%95%B7%E5%BA%A6%E5%8F%88%E8%83%BD%E5%81%9A%E5%88%B0%E5%B9%BE%E5%85%AC%E5%88%86%E5%91%A2%E9%80%99%E9%9B%86%E5%A4%A7%E6%A8%B9%E5%B0%87%E7%82%BA%E6%88%91%E5%80%91%E5%88%86%E4%BA%AB%E4%BB%96%E5%BE%9E%E5%A5%B3%E7%94%9F%E5%88%B0%E7%94%B7%E7%94%9F%E7%B6%93/2926081941001083/",
    "snippet": "FB完整版｜女跨男者親自分享變性手術心得！人造「老 二」超威猛長度大公開！ 你知道女跨男需要經歷哪些手術嗎？人工陰莖的長度又 能做到幾公分呢？這集大樹將為 ..."
  },
  {
    "index": 73,
    "title": "女跨男懷孕生子跨性別伴侶成親生父母創印度首例[影]",
    "link": "https://www.cna.com.tw/news/aopl/202302090390.aspx",
    "snippet": "Feb 9, 2023 — 印度一名跨性別男子今天在南部克勒拉省（Kerala）產下一子後，他和另一半便是具有親生父母身分的跨性別伴侶，創下印度國內首例。"
  },
  {
    "index": 74,
    "title": "有用資料- Transgender Equality Hong Kong 香港跨性別平權協會",
    "link": "http://www.tehk.org.hk/resources_tc.html",
    "snippet": "多元・平等・共融. 女跨男- Nebido 1000mg/4ml Sustanon 250 ... 泰國曼谷伽蒙美容整形外科醫院的目標是成為世界領先的美容和變性手術中心。 男跨女/女跨男性別重置手術."
  },
  {
    "index": 75,
    "title": "女权月月谈“跨性别与女权主义”文字回顾",
    "link": "https://chinesefeminism.org/2022/05/26/%E5%A5%B3%E6%9D%83%E6%9C%88%E6%9C%88%E8%B0%88%E8%B7%A8%E6%80%A7%E5%88%AB%E4%B8%8E%E5%A5%B3%E6%9D%83%E4%B8%BB%E4%B9%89%E6%96%87%E5%AD%97%E5%9B%9E%E9%A1%BE/",
    "snippet": "May 26, 2022 — 关于聊天区对“T/P”所指的问题——丝丝：LGBT的T是指跨性别；在L（女同）中，T是指扮演男性气质的一方，P是扮演女性气质的一方。铁T中有很多是隐形跨男。 中国拉拉 ..."
  },
  {
    "index": 76,
    "title": "台灣首例跨性別男性免術換證高等法院判勝訴 - 公視新聞網",
    "link": "https://news.pts.org.tw/article/697680",
    "snippet": "May 30, 2024 — 這是台灣首次有女性跨男性的跨性別者免術換證勝訴；首起跨性別者成功免術換證案例，是2021年的小E要求性別登記由男改為女，戶政事務所未上訴，已成功變更性別 ..."
  },
  {
    "index": 77,
    "title": "https://zhuanlan.zhihu.com/p/53371146",
    "link": "https://zhuanlan.zhihu.com/p/53371146",
    "snippet": "No information is available for this page."
  },
  {
    "index": 78,
    "title": "[文章分享] 你所不知道的跨性別困境：為何過半民眾對於「免術 ...",
    "link": "https://www.taiwanwomencenter.org.tw/zh-tw/NewsMgt/news/Content/72/news1110924a",
    "snippet": "Sep 24, 2022 — 某些將社會性別認同（Gender）詮釋為光譜的聲音出現，人可以是70％的男性、30％的女性，可以不完全待在全然的單一性別下。又或者性別（Gender）可以是流動的，可以 ..."
  },
  {
    "index": 79,
    "title": "美国“女跨男”游泳选手击败“男跨女”选手，竞赛公平引热议",
    "link": "https://m.thepaper.cn/newsDetail_forward_16221545",
    "snippet": "Jan 10, 2022 — 美国“女跨男”游泳选手击败“男跨女”选手，竞赛公平引热议 ... 当地时间周六（8日），因为两名跨性别运动员，美国常春藤高校联盟一场游泳比赛“火了”。 此前备受争议 ..."
  },
  {
    "index": 80,
    "title": "「很高興認識你」,跨性別者! (XX 的房間導讀)",
    "link": "https://gec.ey.gov.tw/File/8426F7E5C9A57E61?A=C",
    "snippet": "transsexuals ； FTM ）、男變女的跨性人（ male-to-female transsexuals；MTF ... 典型男性或女性染色體等，這些多元多樣的跨性別認同或表. 現均可說是「跨性別 ..."
  },
  {
    "index": 81,
    "title": "【從女變男的心路歷程】自小是緊張大師心境隨性別改變覓平靜",
    "link": "https://www.sbs.com.au/language/chinese/zh-hant/article/hong-kong-transgender-in-australia/nwvg7nzxm",
    "snippet": "Mar 4, 2022 — 除了跨性別人士身份， Kerry亦是一名「無性戀者」及「無戀愛者」，究竟他是如何發現呢？ 現年32歲的Kerry，來自香港，他在15歲時移民澳洲。他出生時的 ..."
  },
  {
    "index": 82,
    "title": "女跨男",
    "link": "https://www.tiktok.com/discover/%E5%A5%B3%E8%B7%A8%E7%94%B7",
    "snippet": "106.4M posts. Discover videos related to 女跨男on TikTok. See more videos about 女女女男男で育った末っ子, 女男男で育った長女, 男が女、女が男夫婦, ..."
  },
  {
    "index": 83,
    "title": "女跨男性別重置手術有哪些？ - 性別詮釋",
    "link": "https://thegendertrans.medium.com/transmen-all-surgery-5550e752c134?source=---------6----------------------------",
    "snippet": "目前在台灣社會，會做這樣的手術診所相當的多，不少女同志和非二元的朋友也會選擇做這個手術來改變自己的身體外貌。這個手術是屬於整形手術的一種，所以不 ..."
  },
  {
    "index": 84,
    "title": "“我在这里”：首位跨性别男性进入日本政坛",
    "link": "https://cn.nytimes.com/asia-pacific/20170522/japanese-transgender-politician-is-showing-i-exist-here/",
    "snippet": "May 22, 2017 — 日本入间——除姓名和头衔外，在一座与东京接壤的城市担任市议员的细田智也(Tomoya Hosoda)的名片上还有一项独一无二的内容。 “出生时为女性”，上面写着。"
  },
  {
    "index": 85,
    "title": "睾酮治疗使“女变男”跨性别男性的免疫反应趋向男性-腾讯新闻",
    "link": "https://news.qq.com/rain/a/20240908A04EP500",
    "snippet": "Sep 8, 2024 — 01. 一项由瑞典卡罗林斯卡医学院、隆德大学和乌普萨拉大学的研究人员合作完成的研究揭示，跨性别男性（即出生性别为女性但自我认同为男性）在接受性别肯定的 ..."
  },
  {
    "index": 86,
    "title": "女跨男| 問題詢問 - 中國醫藥大學附設醫院",
    "link": "https://cmuh.cmu.edu.tw/Question/Detail?no=13376",
    "snippet": "May 15, 2024 — 中國醫藥大學在「世界大學排名」評比， 已經躍登世界頂尖150 大。我們擁有：1)差異化、獨特的全人醫療服務；2）創新技術以滿足病患追求安全、速度與品質之 ..."
  },
  {
    "index": 87,
    "title": "争议大战！跨性别选手的正面交锋，“男跨女”被“女跨男”击败",
    "link": "https://www.sohu.com/a/516175824_121028851",
    "snippet": "Jan 13, 2022 — 近日一场大学泳赛引起各界热论，美国宾夕法尼亚州大学一名跨性别游泳选手Lia Thomas，上月在邀请赛女子组项目打破全国纪录并夺3冠，但近日在一场大学泳赛 ..."
  },
  {
    "index": 88,
    "title": "跨性別社福醫護手冊",
    "link": "https://genderempowerment.org/wp-content/uploads/2017/03/booklet_%E7%A4%BE%E7%A6%8F%E9%86%AB%E8%AD%B7%E6%89%8B%E5%86%8A.pdf",
    "snippet": "也有性別認同不屬於男或女,以及性別認同是會變化的一群。 Q? 這個人一點也不女性化/男性化,他/她怎可能是跨性別!"
  },
  {
    "index": 89,
    "title": "性別重置手術及性別矯正手術",
    "link": "https://wd.vghtpe.gov.tw/ps/Fpage.action?muid=15126&fid=13850",
    "snippet": "Jul 7, 2023 — 申請女變男之變性者，須持經二位精神科專科醫師評估鑑定之診斷書及 ... 更多訊息：跨性別男性、跨性別女性. 「性別矯正手術」. 性發展障礙症候群 ..."
  },
  {
    "index": 90,
    "title": "增加可見度也幫不到我這種非男非女的跨性人",
    "link": "https://www.coolloud.org.tw/node/83979",
    "snippet": "Nov 20, 2015 — 但是這些傑出的跨性人仍傾向於把自己穩穩的放在性別二元中的一邊，也就是從原生性別轉換至相反性別而已，例如男跨女凱特琳·詹納（Caitlyn Jenner）在《浮華 ..."
  },
  {
    "index": 91,
    "title": "難以「跨」越的界線跨性別運動員參賽爭議再起|觀點新世代",
    "link": "https://visionproject.org.tw/story/6656",
    "snippet": "Apr 9, 2023 — 哈伯德（Laurel Hubbard）曾是一位男性舉重選手，在33歲時進行性別激素治療，多年後他以「跨性別女性」的新身分重新參賽，並在43歲時成功取得東京奧運參賽資格， ..."
  },
  {
    "index": 92,
    "title": "“男跨女”游泳输给了“女跨男” 美国网民蒙圈了",
    "link": "https://news.sina.cn/gj/2022-01-10/detail-ikyamrmz4270468.d.html",
    "snippet": "Jan 10, 2022 — 观察者网 ... 当地时间周六（8日），因为两名跨性别运动员，美国常春藤高校联盟一场游泳比赛“火了”。 此前备受争议，在女子比赛中称霸的“男跨女”运动员利娅· ..."
  },
  {
    "index": 93,
    "title": "《2023台灣跨性別族群生活處境報告》暨記者會",
    "link": "https://hotline.org.tw/news/3408",
    "snippet": "Jan 18, 2024 — Viva（跨性別女性）; Deven（跨性別男性）; 畢恆達（國立台灣大學建築與城鄉研究所 ..."
  },
  {
    "index": 94,
    "title": "【奇妙的愛】「女跨男」丈夫為愛停止變性印度首宗跨性別夫婦 ...",
    "link": "https://topick.hket.com/article/3460948/%E3%80%90%E5%A5%87%E5%A6%99%E7%9A%84%E6%84%9B%E3%80%91%E3%80%8C%E5%A5%B3%E8%B7%A8%E7%94%B7%E3%80%8D%E4%B8%88%E5%A4%AB%E7%82%BA%E6%84%9B%E5%81%9C%E6%AD%A2%E8%AE%8A%E6%80%A7%E3%80%80%E5%8D%B0%E5%BA%A6%E9%A6%96%E5%AE%97%E8%B7%A8%E6%80%A7%E5%88%A5%E5%A4%AB%E5%A9%A6%E8%AA%95%E6%84%9B%E5%85%92",
    "snippet": "Feb 14, 2023 — 愛，總能令人誇過一切界限。印度一對跨性別夫婦日前誕下愛兒，成為當地首例。夫婦二人均為跨性別人士，「女跨男」丈夫更為愛暫時終止變性療程， ..."
  },
  {
    "index": 95,
    "title": "【性別平等】女生男身？男生女身？ - 淡江時報",
    "link": "https://tkutimes.tku.edu.tw/dtl.aspx?no=33899",
    "snippet": "... 男生，稱為女跨男FtM (Female to Male)。 以上述例子，小宏屬於跨性別中的MtF，表示屬於生理男性，但其心理為女性，身體是男生，但性別認同是女生，喜歡男性。 Q2 ..."
  },
  {
    "index": 96,
    "title": "马来西亚跨性别者，女跨男！ Hrt的一些变化！ [ 活出喜欢的 ...",
    "link": "https://yandex.ru/video/preview/3761331626651516975"
  },
  {
    "index": 97,
    "title": "首例「女跨男」免術換證勝訴尼莫：終可正大光明說我是男生了",
    "link": "https://today.line.me/tw/v2/article/kEMareM",
    "snippet": "May 29, 2024 — 北市一名生理女「尼莫」，前年申請變更性別遭戶政事務所，以未完整摘除性器官拒絕上訴，台北高等行政法院宣判尼莫勝訴，成全台首例跨男成功案例。尼莫..."
  },
  {
    "index": 98,
    "title": "一個FTM的自我醫療經驗敘說",
    "link": "http://epaper.tame.org.tw/TAME12/category01_page01.html",
    "snippet": "我是一個FTM，也就是Female to Male女跨男的跨性別者，是指原來的生理性別是女性，但其心理性別為男性。 民國84年，我到美國當留學生，當自己對於跨性別尚未了解前，一直以為 ..."
  },
  {
    "index": 99,
    "title": "【精選書摘】我不是想當女人、而是渴望活出自己──日本第一 ...",
    "link": "https://www.twreporter.org/a/bookreivew-kamikawa-aya-the-courage-to-change-my-gender-dysphoria",
    "snippet": "Sep 29, 2021 — 出生時為生理男性、三兄弟家庭的次子，上川礼從小對自己的身體和性別感到困惑，30歲後，開始以女性的身分過活。然而在體制下難以變動的戶籍性別，和社會對跨 ..."
  },
  {
    "index": 100,
    "title": "Vol.4|跨越性别：作为女性被养育十八年后，我终于站在了男",
    "link": "https://podcasts.apple.com/us/podcast/vol-4-%E8%B7%A8%E8%B6%8A%E6%80%A7%E5%88%AB-%E4%BD%9C%E4%B8%BA%E5%A5%B3%E6%80%A7%E8%A2%AB%E5%85%BB%E8%82%B2%E5%8D%81%E5%85%AB%E5%B9%B4%E5%90%8E-%E6%88%91%E7%BB%88%E4%BA%8E%E7%AB%99%E5%9C%A8%E4%BA%86%E7%94%B7%E4%BA%BA%E7%9A%84%E8%B5%B7%E8%B7%91%E7%BA%BF/id1707279593?i=1000627806693",
    "snippet": "Sep 10, 2023 — 缩大是我们身边的一名跨性别男性朋友，三周前来北京进行了女跨男性别重置手术，也促成了我们在东郊的这次相聚。 两次的会面交流中，他分享了他的成长 ..."
  },
  {
    "index": 101,
    "title": "我想當愛男生的男生！ 帥氣跨性別男同志談變性、出櫃歷程",
    "link": "https://gagatai.com/love/relationship/%E6%88%91%E6%83%B3%E7%95%B6%E6%84%9B%E7%94%B7%E7%94%9F%E7%9A%84%E7%94%B7%E7%94%9F%EF%BC%81-%E5%B8%A5%E6%B0%A3%E8%B7%A8%E6%80%A7%E5%88%A5%E7%94%B7%E5%90%8C%E5%BF%97%E8%AB%87%E8%AE%8A%E6%80%A7%E3%80%81%E5%87%BA%E6%AB%83%E6%AD%B7%E7%A8%8B",
    "snippet": "Jul 5, 2023 — 漫或是性的層面受到哪種性別吸引，像是異性戀、同性戀、雙性戀等等。 中國YouTuber Jay 先前曾訪問一位女跨男的同性戀（FTM G, Female to Male Gay）賣力， ..."
  },
  {
    "index": 102,
    "title": "人們可以決定自己的性別嗎？",
    "link": "https://plainlaw.me/posts/gender-self-determination",
    "snippet": "Mar 15, 2022 — 跨性別女性摘除男性生殖器官、改造成女性生殖器官及隆乳手術，費用約 ... 男跨女受刑人與生理女性共處監獄，甚而發生性騷擾或性侵的案件，也同樣 ..."
  },
  {
    "index": 103,
    "title": "TVBS新聞網| 【帥暈！女跨男變性外表超Man 親曝「D罩杯→ ...",
    "link": "https://www.instagram.com/tvbslivenews/p/CcfyU-mP3Sh/",
    "snippet": "1364 likes, 19 comments - tvbslivenews on April 18, 2022: \"【帥暈！女跨男變性外表超Man 親曝「D罩杯→平胸」辛苦過程】不仔細看，看不出原來是女生欸   #改造#變性# ..."
  },
  {
    "index": 104,
    "title": "台灣跨性別者倡議免術換證，人權與治安能否平衡？【獨立 ...",
    "link": "https://www.womengroups.org.tw/OnePage.aspx?tid=1&id=589",
    "snippet": "Mar 29, 2022 — 強烈的內心矛盾驅使著吳伊婷，不斷地自我探索，直到他終於確定，住在自己男生身體裡的，根本是個女生。此後，吳伊婷選擇忠於自我，不但改穿女裝，還改了名字，以 ..."
  },
  {
    "index": 105,
    "title": "准变性人Q拟覆核婚姻修例(图)",
    "link": "http://www.mingshengbao.com/van/article.php?aid=212357",
    "snippet": "Jul 7, 2014 — ... 女跨男准变性人Q提请司法覆核，挑战一旦通过后将强制跨性别人接受全套变性手术，方可以新性别跟异性结婚的《2014年婚姻（修订）条例》，而Q则透过电话 ..."
  },
  {
    "index": 106,
    "title": "跨性別運動員爭議不斷，美國游泳賽「男跨女」vs「女跨男」",
    "link": "https://fitz.hk/sports/swimming/%E8%B7%A8%E6%80%A7%E5%88%A5%E9%81%8B%E5%8B%95%E5%93%A1%E7%88%AD%E8%AD%B0%E4%B8%8D%E6%96%B7%EF%BC%8C%E7%BE%8E%E5%9C%8B%E6%B8%B8%E6%B3%B3%E8%B3%BD%E3%80%8C%E7%94%B7%E8%B7%A8%E5%A5%B3%E3%80%8Dvs%E3%80%8C/",
    "snippet": "Jan 10, 2022 — Lia 原是賓州大學男子游手，接受手術後，服用了一年雄性激素抑壓劑，取得女子參賽資格。在上個月比賽中，Lia 於200米自由式游出1分41.93秒、500米自由式游出4 ..."
  },
  {
    "index": 107,
    "title": "跨男終極上訴得直未完成完整性別重置手術者可更改身份證 ...",
    "link": "http://www.inmediahk.net/node/%E7%A4%BE%E9%81%8B/%E8%B7%A8%E7%94%B7%E7%B5%82%E6%A5%B5%E4%B8%8A%E8%A8%B4%E5%BE%97%E7%9B%B4-%E6%9C%AA%E5%AE%8C%E6%88%90%E5%AE%8C%E6%95%B4%E6%80%A7%E5%88%A5%E9%87%8D%E7%BD%AE%E6%89%8B%E8%A1%93%E8%80%85-%E5%8F%AF%E6%9B%B4%E6%94%B9%E8%BA%AB%E4%BB%BD%E8%AD%89%E6%80%A7%E5%88%A5",
    "snippet": "Feb 6, 2023 — 【獨媒報導】兩名自小認定為男性的跨性別人士，因未完成由女轉男的完整性別重置手術，不獲入境處准許將身份證上性別改為男性。兩人認為政策侵犯人權， ..."
  },
  {
    "index": 108,
    "title": "性少數中的少數——同婚之後，跨性別者的階段性勝利在何方？",
    "link": "https://www.verse.com.tw/article/lgbtq-trans",
    "snippet": "Jan 11, 2023 — ... 跨性身分被認出。至於女跨男，還需要面對不被看見的問題。 光是證明自己存在就很難了. 「跨男使用賀爾蒙之後，聲音外貌就會改變，相較於跨女需要搭配臉 ..."
  },
  {
    "index": 109,
    "title": "【女跨男變性獲新生Man爆！他嘆能「站著尿尿」超感動】 | 天啊 ...",
    "link": "https://www.facebook.com/wwwttshow/videos/448138933750520/"
  },
  {
    "index": 110,
    "title": "跨性別彙整",
    "link": "https://www.goh.org.tw/perspectives_tag/%E8%B7%A8%E6%80%A7%E5%88%A5/",
    "snippet": "【男人想想】一位女跨男的自敘：我的「pass」之路. 2019年10月25日，同志遊行的 ... 【愛馨學園】在姊妹的庇護所之外：跨性別女性受暴經驗. 根據美國全國聯合反暴力 ..."
  },
  {
    "index": 111,
    "title": "辣台妹聊性別- 【你到底是男是女？跨性別者在媒體鏡頭窺伺 ...",
    "link": "https://www.facebook.com/TaimeiGenderBar/posts/%E4%BD%A0%E5%88%B0%E5%BA%95%E6%98%AF%E7%94%B7%E6%98%AF%E5%A5%B3%E8%B7%A8%E6%80%A7%E5%88%A5%E8%80%85%E5%9C%A8%E5%AA%92%E9%AB%94%E9%8F%A1%E9%A0%AD%E7%AA%BA%E4%BC%BA%E4%B8%8B%E7%9A%84%E5%BD%A2%E8%B1%A1%E5%B0%8Fa%E8%BE%A3%E9%8D%BE%E6%98%8E%E8%BB%92alizabeth%E5%A8%98%E5%A8%98%E9%83%BD%E6%98%AF%E9%80%99%E5%B9%BE%E5%B9%B4%E7%9B%B8%E7%95%B6%E7%9F%A5%E5%90%8D%E7%9A%84%E7%B6%B2%E7%B4%85%E9%9B%96%E7%84%B6%E6%9C%89%E8%87%AA%E5%B7%B1%E7%9A%84youtube%E9%A0%BB%E9%81%93%E4%BB%96%E5%80%91%E4%BB%8D%E7%84%B6%E4%B8%8D%E5%8F%AF%E8%BA%B2%E9%81%BF%E5%AA%92%E9%AB%94%E9%96%83%E5%85%89%E7%87%88%E5%BE%9E/803870737011352/",
    "snippet": "做到什麼程度才 算是一個「女人」？ ... 不同於男同志或女同志，跨性別者或者是「偽娘」的櫃 子其實是「透明」的，他們不像同性戀者，可以躲在「 深櫃」假裝是異 ..."
  },
  {
    "index": 112,
    "title": "【跨男產子】「男人產子」是「罕見例外」？ 澳洲至少294宗 ...",
    "link": "https://blog.scs.org.hk/2023/04/13/%E3%80%90%E8%B7%A8%E7%94%B7%E7%94%A2%E5%AD%90%E3%80%91%E3%80%8C%E7%94%B7%E4%BA%BA%E7%94%A2%E5%AD%90%E3%80%8D%E6%98%AF%E3%80%8C%E7%BD%95%E8%A6%8B%E4%BE%8B%E5%A4%96%E3%80%8D%EF%BC%9F-%E6%BE%B3%E6%B4%B2/",
    "snippet": "Apr 13, 2023 — 跨性別男性仍能懷孕？跨性別男性原為生理女性，如果他們沒有切除自己生來的女性生殖系統，包括卵巢、子宮等等，即使在..."
  },
  {
    "index": 113,
    "title": "我男友的性别是女跨男，我以后要注意什么问题",
    "link": "https://www.bilibili.com/video/BV18u4y1M7Ev/",
    "snippet": "Dec 18, 2023 — 我男友的性别是女跨男，我以后要注意什么问题. 龙飞律师. 相关推荐. 查看更多. 跨性别男性-花时12小时跨省做乳头修除手术."
  },
  {
    "index": 114,
    "title": "女跨男",
    "link": "https://www.tiktok.com/tag/%E5%A5%B3%E8%B7%A8%E7%94%B7",
    "snippet": "女跨男|在TikTok 上觀看關於#女跨男的最新影片。"
  },
  {
    "index": 115,
    "title": "遭遇家长威胁| 跨性别手术医生那些不为人知的事",
    "link": "https://m.douban.com/note/732630741/",
    "snippet": "Sep 1, 2019 — 跨性别女性(Transgender Woman)：指认同自己是女性的跨性别者，又称男跨女（MTF）。性别酷儿（Gender queer）：指认同自己既不完全属于男性也不完全属于女性的人， ..."
  },
  {
    "index": 116,
    "title": "反過來談女跨男好了如果照河道上看到的資訊,一定要手術才 ...",
    "link": "https://www.threads.net/@judoyang/post/DBMQJDES1a5",
    "snippet": "Oct 16, 2024 — ... 跨性別以台灣女跨男如果不能免術的的話那女跨男照要手術才能跨男的標準卵巢+子宮必須摘除+胸部要縮乳手術並且要在手術消除陰道在做一個假GG 還要男性 ..."
  },
  {
    "index": 117,
    "title": "認識跨性別者及其處境《解答》 - 永無止盡的學習路",
    "link": "https://roddayeye.pixnet.net/blog/post/337703573",
    "snippet": "Jan 23, 2023 — 根據2008年內授中戶字第0970066240號，申請男變女之變性者，須持經二位精神科專科醫師評估鑑定之診斷書及合格醫療機構開具已摘除男性性器官，包括陰莖及睪丸 ..."
  },
  {
    "index": 118,
    "title": "「生理女」太帥遭霸凌？3大性別認同問題有解",
    "link": "https://helloyishi.com.tw/mental-health/other-mental-health-issues/what-you-should-know-about-gender-identity/",
    "snippet": "Nov 29, 2022 — 許多人在稱讚女跨男的跨性別者時，會無意間使用可能帶有歧視意味的表達方式，造成對方尷尬，甚至內心受傷害。 舉例來說，今天跨性別男性打扮的特別帥氣，有人卻 ..."
  },
  {
    "index": 119,
    "title": "我是心理跨性别者，女跨男。我该怎么办？",
    "link": "https://www.xinli001.com/qa/100531763",
    "snippet": "我是单亲家庭.刚出生甚至刚成型被知道是个女孩就被父亲那边人抛弃扔掉被姥姥抱了回来.我的妈妈从小因病智力不怎么好.姥姥是个老师给我灌输思想.不让我留长发."
  },
  {
    "index": 120,
    "title": "「跨男」贏終審可望換身份證正性別6年兩邊不是人等到遲來公義",
    "link": "https://www.hk01.com/%E7%A4%BE%E6%9C%83%E6%96%B0%E8%81%9E/864415/%E8%B7%A8%E7%94%B7-%E8%B4%8F%E7%B5%82%E5%AF%A9%E5%8F%AF%E6%9C%9B%E6%8F%9B%E8%BA%AB%E4%BB%BD%E8%AD%89%E6%AD%A3%E6%80%A7%E5%88%A5-6%E5%B9%B4%E5%85%A9%E9%82%8A%E4%B8%8D%E6%98%AF%E4%BA%BA%E7%AD%89%E5%88%B0%E9%81%B2%E4%BE%86%E5%85%AC%E7%BE%A9",
    "snippet": "Feb 7, 2023 — 謝浩霖原生性別為女性，自我認同為男性，已服用男性荷爾蒙藥物及切去乳房，隨後於2016年獲英國的性別承認證書，以男性身份於當地擁有法律權利。他翌年回流香港 ..."
  },
  {
    "index": 121,
    "title": "先生？小姐？跨性別者怎麼稱呼- 事出有影",
    "link": "https://newslab.pts.org.tw/video/229",
    "snippet": "Mar 29, 2023 — ... 男生／女生或非二元的其他認同。跨性別者即為性別認同與生理性別不同者，例如，生理特徵為男性，自我認同為女性，稱為「跨女」，反之為「跨男」，還有 ..."
  },
  {
    "index": 122,
    "title": "“生而无罪，你不需要抱歉”|性别认同：“顺”或“跨”都不该被轻易 ...",
    "link": "https://xinli.swjtu.edu.cn/info/1065/5833.htm",
    "snippet": "Oct 13, 2021 — 在此，伞状术语范围内的个体可能认同于与此相关的一系列术语，如跨性别男性、跨性别女性、异装、非二元性别等。 ... 2、幼儿期：我开始思考自己是“男”是“女”？"
  },
  {
    "index": 123,
    "title": "做跨性手術前還要先演戲？ 讓跨性別者陷入難關的精神鑑定",
    "link": "https://newslab.nccu.edu.tw/PageDoc/Detail?fid=10782&id=23245",
    "snippet": "Jun 23, 2023 — 但在台灣，要改變性別前，必須要看精神科。他17歲走進診間，沒想到醫生的問題私密，像是性幻想對象是男生還是女生、看什麼樣的A ..."
  },
  {
    "index": 124,
    "title": "【Long game】陳子軒／運動場的終極難題：跨性別與性別發展 ...",
    "link": "https://www.twreporter.org/a/saturday-features-long-game-transgender-dsd-athletes",
    "snippet": "Apr 8, 2022 — 光就生理檢測性別本身，就有一些人具先天的性別發展差異（Differences in Sexual Development, DSD），難以用科學檢測方法，進行男性或女性的性別二分法認定。"
  },
  {
    "index": 125,
    "title": "【不一樣又怎樣ep.15】跨性别男神如何追女生？各种撩妹法 ...",
    "link": "https://www.youtube.com/watch?v=L3-nBYtTQ7w"
  },
  {
    "index": 126,
    "title": "跨性別身份案：一名香港「跨仔」爭取證件上性別的正名之路| 「我 ...",
    "link": "https://www.facebook.com/bbcnewstrad/videos/%E8%B7%A8%E6%80%A7%E5%88%A5%E8%BA%AB%E4%BB%BD%E6%A1%88%E4%B8%80%E5%90%8D%E9%A6%99%E6%B8%AF%E8%B7%A8%E4%BB%94%E7%88%AD%E5%8F%96%E8%AD%89%E4%BB%B6%E4%B8%8A%E6%80%A7%E5%88%A5%E7%9A%84%E6%AD%A3%E5%90%8D%E4%B9%8B%E8%B7%AF/563747935770181/"
  },
  {
    "index": 127,
    "title": "跨性別遊行2000人夜行西門町疾呼「免術換證」是人權",
    "link": "https://www.civilmedia.tw/archives/129048",
    "snippet": "6 days ago — 近日網路上「反跨」言論延燒，10月初時藝人鄭家純在個人平台提出「生理女 ... 熱線諮詢協會跨性別小組志工湯姆是一位跨男，他說明自己歷經9年更換法定 ..."
  },
  {
    "index": 128,
    "title": "【27歲女變性成男同志大公開性別認同跨GAY艱辛過程曝 ...",
    "link": "https://www.youtube.com/watch?v=RIOXyp4qOS0"
  },
  {
    "index": 129,
    "title": "YouTube搶先看｜女跨男者親自分享變性手術心得！人造「老二 ...",
    "link": "https://www.facebook.com/memediatw/videos/youtube%E6%90%B6%E5%85%88%E7%9C%8B%E5%A5%B3%E8%B7%A8%E7%94%B7%E8%80%85%E8%A6%AA%E8%87%AA%E5%88%86%E4%BA%AB%E8%AE%8A%E6%80%A7%E6%89%8B%E8%A1%93%E5%BF%83%E5%BE%97%E4%BA%BA%E9%80%A0%E8%80%81%E4%BA%8C%E8%B6%85%E5%A8%81%E7%8C%9B%E9%95%B7%E5%BA%A6%E5%A4%A7%E5%85%AC%E9%96%8B/107067644714112/?locale=hu_HU"
  },
  {
    "index": 130,
    "title": "男跨女",
    "link": "https://en.wiktionary.org/wiki/%E7%94%B7%E8%B7%A8%E5%A5%B3",
    "snippet": "... woman; daughter. trad. (男跨女), 男 · 跨 · 女 · simp. #(男跨女), 男 · 跨 · 女 · Wikipedia has an article on: 跨性別女性. Pronunciation. edit · Mandarin. (Pinyin) ..."
  },
  {
    "index": 131,
    "title": "JK罗琳说跨性别女性是男人，被舆论围攻，甚至被哈利波特 ...",
    "link": "https://www.163.com/dy/article/JFRIMGJV0543D9PX.html",
    "snippet": "1 day ago — 这是个女人？ 乔纳森·范·内斯是一个跨性别者，他嫁给了一个男人。它对罗琳的言论很生气，它说：“跨性女性就是女性。变性黑人和非变性黑人每天都受到 ..."
  },
  {
    "index": 132,
    "title": "跨性別運動權-你所不知道的事",
    "link": "https://www.youtube.com/watch?v=kgjY9DD16sg"
  },
  {
    "index": 133,
    "title": "帥暈！女跨男變性外表超Man 親曝「D罩杯→平胸」辛苦過程| 【帥 ...",
    "link": "https://www.facebook.com/tvbsfb/videos/%E5%B8%A5%E6%9A%88%E5%A5%B3%E8%B7%A8%E7%94%B7%E8%AE%8A%E6%80%A7%E5%A4%96%E8%A1%A8%E8%B6%85man-%E8%A6%AA%E6%9B%9Dd%E7%BD%A9%E6%9D%AF%E5%B9%B3%E8%83%B8%E8%BE%9B%E8%8B%A6%E9%81%8E%E7%A8%8B/714021292957874/"
  },
  {
    "index": 134,
    "title": "跨性別｜喝下轉骨湯就輸了？困在女生身體的少年掙脫性別刻板 ...",
    "link": "https://www.youtube.com/watch?v=XL07Xj40VCw"
  },
  {
    "index": 135,
    "title": "跨性別",
    "link": "https://www.dcard.tw/topics/%E8%B7%A8%E6%80%A7%E5%88%A5",
    "snippet": "跨性別 · 川普反跨性別廣告拉攏未表態選民專家警告恐釀反效果 · 真的很猶豫 · 萬聖節  裝扮 · 男娘宿舍之臭豆腐泡麵 · 請推薦高雄市雷射除毛 · FTM 肌肉注射腫起來，大家都這樣嗎  ."
  },
  {
    "index": 136,
    "title": "Mass.Gov Search",
    "link": "https://search.mass.gov/",
    "snippet": "The official search application of the Commonwealth of Massachusetts. Search the Commonwealth's web properties to more easily find the services and ..."
  },
  {
    "index": 137,
    "title": "【女跨男超Man外表帥翻網！Dcup→平胸大談變性過程】 | 直接被 ...",
    "link": "https://www.facebook.com/wwwttshow/videos/%E5%A5%B3%E8%B7%A8%E7%94%B7%E8%B6%85man%E5%A4%96%E8%A1%A8%E5%B8%A5%E7%BF%BB%E7%B6%B2dcup%E5%B9%B3%E8%83%B8%E5%A4%A7%E8%AB%87%E8%AE%8A%E6%80%A7%E9%81%8E%E7%A8%8B/1040711913533382/"
  },
  {
    "index": 138,
    "title": "闪婚闪离”多地频发，相亲到领证多在3天内完成",
    "link": "https://www.jfdaily.com/news/detail?id=813038",
    "snippet": "2 days ago — “父母重男轻女，没办法。”家里准备的30多万元中，有12万元是小曾男朋友给的彩礼。 “闪婚”是70岁爸爸 ..."
  },
  {
    "index": 139,
    "title": "Marion Technical College",
    "link": "https://www.mtc.edu/",
    "snippet": "About MTC; Academic Programs; Admissions & CCP; Financial Aid; Student Resources; Campus Info; Community; Workforce Solutions; Alumni & Giving. Tookit Icon ..."
  },
  {
    "index": 140,
    "title": "當男當女不須醫療評估德國性別自決法11月上路",
    "link": "https://udn.com/news/story/6812/8323335",
    "snippet": "4 days ago — 目前為止，跨性別、雙性人和非二元性別者，如果想要更改自己的性別，必須經過至少兩名心理醫師評估，以及通過法院許可等，一連串重重障礙和昂貴的程序，才能正式 ..."
  },
  {
    "index": 141,
    "title": "易建聯嫖跨性別者?︱男主沉默6日突留言「Fake News」 似 ...",
    "link": "https://std.stheadline.com/realtime/article/2030790/%E5%8D%B3%E6%99%82-%E4%B8%AD%E5%9C%8B-%E6%98%93%E5%BB%BA%E8%81%AF%E5%AB%96%E8%B7%A8%E6%80%A7%E5%88%A5%E8%80%85-%EF%B8%B1%E7%94%B7%E4%B8%BB%E6%B2%89%E9%BB%986%E6%97%A5%E7%AA%81%E7%95%99%E8%A8%80-Fake-News-%E4%BC%BC%E5%8F%8D%E6%93%8A%E9%86%9C%E8%81%9E",
    "snippet": "Oct 21, 2024 — 易建聯沉默6日後，約在社交平台發文「Fake News」二字，似在回應此宗醜聞。 相關新聞： 易建聯嫖跨性別者?︱事發於北京五星級酒店？ 疑似「女主角」機場被警帶 ..."
  },
  {
    "index": 142,
    "title": "“跨省闪婚”调查：有女子领证9个月生孩子男方做鉴定发现不是 ...",
    "link": "https://news.qq.com/rain/a/20241030A087AE00",
    "snippet": "2 days ago — 01红星新闻调查发现，全国多个省份均有跨省“闪婚”现象，其中牵线搭桥的中介大多与贵州婚介有合作。 · 02受害者多为经济条件较差、性格内向的男性，女方年龄 ..."
  },
  {
    "index": 143,
    "title": "A. O. Smith: Gas & Electric Water Heaters & Tankless Models",
    "link": "https://www.hotwater.com/",
    "snippet": "Find residential and commercial tankless models, hybrid heat pumps and storage tanks. Explore A. O. Smith's line of gas and electric water heaters."
  },
  {
    "index": 144,
    "title": "入境處聯同內地執法機關搗破跨境偽證集團（附圖）",
    "link": "https://www.info.gov.hk/gia/general/202410/31/P2024103100565.htm",
    "snippet": "1 day ago — 該十名集團主腦及骨幹成員，分別為五男五女，當中包括七名內地居民及三名香港居民，年齡介乎十八至六十一歲。而六十七名被捕的懷疑非法勞工為三十四男 ..."
  },
  {
    "index": 145,
    "title": "先生？小姐？怎麼不失禮不尷尬稱呼跨性別者｜公視P# 新聞 ...",
    "link": "https://www.youtube.com/watch?v=sqPzYHA_x78"
  },
  {
    "index": 146,
    "title": "女性影展｜當色情片不再是男性的遊戲——從《色愛》窺看 ...",
    "link": "https://everylittled.com/article/192053",
    "snippet": "5 days ago — 過沒多久，捲髮女人跨坐在男人身上，與長髮女人來一場悠長的濕吻，畫面特寫她們盛滿慾望的表情與激情四射的親密互動，兩側時不時夾帶一些因膠卷劣化導致的雜訊 ..."
  },
  {
    "index": 147,
    "title": "GD2024090602ZP01GS宁波市市域铁路投资发展有限公司 ...",
    "link": "http://gzw.ningbo.gov.cn/art/2024/11/1/art_1229671220_4457313.html",
    "snippet": "14 hours ago — ... 杭州湾跨海大桥航道桥. 建工&建乐-财富中心 ... 女. 30. 西南交通大学. 交通运输（城市轨道交通方向）. 大学本科. 运营技术管理岗（站务）. 3. 朱屹东. 男."
  },
  {
    "index": 148,
    "title": "性别确认手术| Bangkok Hospital",
    "link": "https://www.bangkokhospital.com/zh/content/sex-affirmation-surgery",
    "snippet": "男性变女性手术. 男变女手术是将男性的阴茎从外观和功能上转变为女性的生殖器，包括外阴唇、内阴唇、尿道 ..."
  },
  {
    "index": 149,
    "title": "FB完整版｜大叔曾經是女人？！女跨男真實案例做最真實的 ...",
    "link": "https://www.facebook.com/memediatw/videos/fb%E5%AE%8C%E6%95%B4%E7%89%88%E5%A4%A7%E5%8F%94%E6%9B%BE%E7%B6%93%E6%98%AF%E5%A5%B3%E4%BA%BA%E5%A5%B3%E8%B7%A8%E7%94%B7%E7%9C%9F%E5%AF%A6%E6%A1%88%E4%BE%8B-%E5%81%9A%E6%9C%80%E7%9C%9F%E5%AF%A6%E7%9A%84%E8%87%AA%E5%B7%B1/799811137324309/?locale=sv_SE"
  },
  {
    "index": 150,
    "title": "罪犯變態無論什麼情況都會有，但因為這些人去 ...",
    "link": "https://x.com/shaketo88/status/1851869911167177067",
    "snippet": "2 days ago — SunshineKio 但不能因為有變態，去忽視其他真正有需求人的權益討論，跨性不只男跨女，女跨男也有免術換證的議題，罪犯變態無論什麼情況都會有， ..."
  },
  {
    "index": 151,
    "title": "大家好大家好我是跨男Deven大家好",
    "link": "https://www.youtube.com/watch?v=iflb04o9ci0"
  },
  {
    "index": 152,
    "title": "Hang Ten",
    "link": "https://tw.shophangten.com/",
    "snippet": "... 男長褲女長褲外套跨氣候穿著男T恤戶外外套短袖男吸濕快乾女跨世代穿著女T恤."
  },
  {
    "index": 153,
    "title": "2024/25赛季ISU短道速滑世界巡回赛第二站蒙特利尔站：前瞻",
    "link": "https://olympics.com/zh/news/isu-short-track-world-tour-second-stage-montreal-preview",
    "snippet": "3 days ago — ... 跨北美、亚洲和欧洲。 ... 世界巡回赛的比赛形式为每个周末进行三个个人项目（500米、1000米和1500米）的角逐，汇集所有顶尖选手，以及男女子接力和混合接力比赛 ..."
  },
  {
    "index": 154,
    "title": "當男當女不須醫療評估德國性別自決法11月上路",
    "link": "https://udn.com/news/story/6812/8323335?from=udn-catelistnews_ch2",
    "snippet": "4 days ago — 目前為止，跨性別、雙性人和非二元性別者，如果想要更改自己的性別，必須經過至少兩名心理醫師評估，以及通過法院許可等，一連串重重障礙和昂貴的程序，才能正式 ..."
  },
  {
    "index": 155,
    "title": "跨性別板",
    "link": "https://www.dcard.tw/f/trans",
    "snippet": "... ♂️）的接受程度- Dcard，原本覺得女生比較重視內在個性，對於性方面考量可能還好，以為大多數異女都能接受跨男  ‍♂️，結果看了投票……唉～竟然有近2/3的異女連做完GG的跨男也無法."
  },
  {
    "index": 156,
    "title": "香港海關破獲兩宗毒品案件並檢獲約一千萬元懷疑毒品（附圖）",
    "link": "https://www.info.gov.hk/gia/general/202410/29/P2024102900426.htm",
    "snippet": "3 days ago — 首宗案件涉及一名六十四歲的男旅客和一名五十九歲的女旅客，兩人十月二十七日從法國巴黎飛抵本港。海關人員清關時，在他們的寄艙行李檢獲共約八公斤 ..."
  },
  {
    "index": 157,
    "title": "微小的反抗：当职场女性开始觉醒",
    "link": "https://m.huxiu.com/article/3635616.html",
    "snippet": "15 hours ago — 阿允还看到，女同事似乎比男同事更不自信。她于是一有机会就夸她们，起初 ... 比如在与老板的会议或者跨部门会议上，她会更主动参与讨论和发言 ..."
  },
  {
    "index": 158,
    "title": "女子20歲變性成男人，長出男性器官後卻後悔了，27歲又做手術 ...",
    "link": "https://www.youtube.com/watch?v=MuXKJDSLjkw"
  },
  {
    "index": 159,
    "title": "MAKENNA 斜跨包BTFA2405",
    "link": "https://www.beside-u.com.tw/products/makenna-crossbody-btfa2405",
    "snippet": "女包系列 · BNU 都會系列 · BFY 輕旅系列 · BSZ 簡約系列 · BNUP 繽紛系列 · BTFA 水果系列 · 男包系列 ... MAKENNA 斜跨包BTFA2405. 功能列表 尺寸: 26x 20.5 x 14 cm 外部："
  },
  {
    "index": 160,
    "title": "宁波市第二十六届高层次人才智力引进洽谈会宁波华润兴光燃气 ...",
    "link": "http://gzw.ningbo.gov.cn/art/2024/11/1/art_1229671220_4457362.html",
    "snippet": "13 hours ago — ... 杭州湾跨海大桥航道桥. 建工&建乐-财富中心工程2017年获国家优质 ... 女. 2000.04. 硕士研究生. 中共党员. 华东理工大学. 机械. 生产运行. 严晓斌. 男."
  },
  {
    "index": 161,
    "title": "【开箱】《阿诺拉》 风月俏佳人玻璃鞋碎裂(图)",
    "link": "http://www.mingshengbao.com/van/article.php?aid=936974",
    "snippet": "9 hours ago — 辛贝克拍的电影不算主流，由早期的《小明星》、《跨性有话儿》，到 ... 女敌两男，完全展现烈女本色，这一几x??出无穷活力。 《阿诺拉》大致可 ..."
  },
  {
    "index": 162,
    "title": "日本“推活”最前线",
    "link": "https://cn.nikkei.com/columnviewpoint/column/57077-2024-11-01-05-00-03.html",
    "snippet": "23 hours ago — ... 跨服务、电影、音乐等娱乐范畴的名称都排列在了一起（具有漫画、动画 ... 沿着男性占50％、女性占50％的线排列的是《鬼灭之刃》、《咒术回战》 ..."
  },
  {
    "index": 163,
    "title": "從女性跨性別為男性，選擇扮成女生來演出？我就像其他化變裝 ...",
    "link": "https://m.youtube.com/watch?v=tEoNDlh_GYY&pp=ygUNI-i3qOaAp-WIq-iAhQ%3D%3D"
  },
  {
    "index": 164,
    "title": "美國浙商物流電商協會成立促進雙方跨境業務",
    "link": "https://www.worldjournal.com/wj/story/121471/8332616?from=wj_catelistnews_index",
    "snippet": "3 hours ago — ... 跨境業務成長。 UZLEA ... 男行刑式射殺庭審揭秘辛. 2024-10-29 22:02 · 華裔女子Hannah Chea剝牡蠣賺取收入。（Hannah Chea Instagram帳號）. 加州華女 ..."
  },
  {
    "index": 165,
    "title": "2024 第二屆金V 獎入圍名單公布跨領域多元表現成活動焦點",
    "link": "https://gnn.gamer.com.tw/detail.php?sn=276045",
    "snippet": "13 hours ago — ... 女V 獎」四獎項成為入圍最多的創作者受到矚目，名雪薇薇也同時入圍三個獎項，展現跨領域發展的潛力。然而，本屆「年度最佳男V 獎」因投稿數量僅有11 ..."
  },
  {
    "index": 166,
    "title": "两度离婚港姐65岁男星合唱“神秘索女”",
    "link": "https://www.chinapress.com.my/20241031/%E4%B8%A4%E5%BA%A6%E7%A6%BB%E5%A9%9A%E6%B8%AF%E5%A7%90-65%E5%B2%81%E7%94%B7%E6%98%9F%E5%90%88%E5%94%B1%E7%A5%9E%E7%A7%98%E7%B4%A2%E5%A5%B3/",
    "snippet": "1 day ago — （香港讯）65岁“鬼才”林敏骢多才多艺，除为著名填词人，同时身兼演员、主持及跨媒体创作人，也被誉为香港“无厘头”始祖。林敏骢首次拍剧集《下流上车族》便 ..."
  },
  {
    "index": 167,
    "title": "入境處聯同內地破跨境偽證集團拘逾200人被捕黑工日薪500 ...",
    "link": "https://news.mingpao.com/ins/%E6%B8%AF%E8%81%9E/article/20241031/s00001/1730364626066/%E5%85%A5%E5%A2%83%E8%99%95%E8%81%AF%E5%90%8C%E5%85%A7%E5%9C%B0%E7%A0%B4%E8%B7%A8%E5%A2%83%E5%81%BD%E8%AD%89%E9%9B%86%E5%9C%98%E6%8B%98%E9%80%BE200%E4%BA%BA-%E8%A2%AB%E6%8D%95%E9%BB%91%E5%B7%A5%E6%97%A5%E8%96%AA500%E8%87%B31200%E5%85%83",
    "snippet": "1 day ago — 行動中，調查員喬裝成速遞員，在全港各區進行管控派遞包裹行動，同時突擊搜查69個目標地點，包括37個住宅單位以及32個工作地點，成功拘捕52男45女 ..."
  },
  {
    "index": 168,
    "title": "前三季度全国跨省异地就医直接结算1.7亿人次 - 湖南- 中国新闻网",
    "link": "http://www.hn.chinanews.com.cn/news/gnxw/2024/1101/500729.html",
    "snippet": "13 hours ago — 本报讯(记者李丹青)记者近日从国家医保局获悉，今年前三季度，全国跨 ... 男、女主角奖。电视剧《三体》获最佳电视剧，其导演杨磊获最佳电视剧导 ..."
  },
  {
    "index": 169,
    "title": "“跨境理财通”扩容！首批14家券商名单公布",
    "link": "https://news.dayoo.com/finance/202411/01/171077_54740541.htm",
    "snippet": "11 hours ago — ... 男团1/4决赛中发生了令人揪心的一幕。 2024-11-01 14:46. 中国足协信息化 ... 中国女冰以5:0战胜哈萨克斯坦队，收获“开门红”。 2024-10-31 22:50."
  },
  {
    "index": 170,
    "title": "CHRISTINA 斜肩包BTFA2412",
    "link": "https://www.beside-u.com.tw/products/christina-crossbody-btfa2412",
    "snippet": "女包系列 · BNU 都會系列 · BFY 輕旅系列 · BSZ 簡約系列 · BNUP 繽紛系列 · BTFA 水果系列 · 男包系列 · 後背包Backpacks · 斜跨包Crossbody Bags · 所有款式 · 後背包 ..."
  },
  {
    "index": 171,
    "title": "東方日報A1：跨境集團派偽證供宿位打造黑工經濟",
    "link": "https://hk.on.cc/hk/bkn/cnt/news/20241101/bkn-20241101033017838-1101_00822_001.html",
    "snippet": "1 day ago — 入境處高級首席入境事務主任（執法）蘇駿豪表示，在代號「領鋒」行動中，調查員突擊搜查69個目標地點，包括37個住宅和32個工作地點，並拘捕52男45女共97人（18至 ..."
  },
  {
    "index": 172,
    "title": "【男跨女變性手術費用曝光動刀花百萬網喊：好勇敢】@AllieAllie",
    "link": "https://www.youtube.com/watch?v=yzb-UycU1eo"
  },
  {
    "index": 173,
    "title": "数百人“女朋友”被抓了！警方披露详情，广东也有→",
    "link": "https://m.gmw.cn/2024-11/01/content_1303886389.htm",
    "snippet": "14 hours ago — 类似的案件早已不是第一次发生。2021年9月16日，针对“女聊手”专撩男用户要礼物打赏诈骗，广东茂名警方捣毁12个网络交友诈骗窝点31人落网。 除了索要打赏的."
  },
  {
    "index": 174,
    "title": "外籍男子被控谋杀印尼籍女子案件押至明年1月再讯",
    "link": "https://gbcode.rthk.hk/TuniS/news.rthk.hk/rthk/ch/component/k2/1777180-20241101.htm",
    "snippet": "15 hours ago — 一名25岁印尼籍女子星期一被发现倒毙于香港仔瀑布湾公园瀑布底，34岁外籍男子被控谋杀罪，他36岁的港人妻子因涉嫌协助罪犯被捕。"
  },
  {
    "index": 175,
    "title": "女傭陳屍瀑布灣外籍男北上返港被捕- 20241030 - 港聞",
    "link": "https://news.mingpao.com/pns/%E6%B8%AF%E8%81%9E/article/20241030/s00002/1730226682358/%E5%A5%B3%E5%82%AD%E9%99%B3%E5%B1%8D%E7%80%91%E5%B8%83%E7%81%A3-%E5%A4%96%E7%B1%8D%E7%94%B7%E5%8C%97%E4%B8%8A%E8%BF%94%E6%B8%AF%E8%A2%AB%E6%8D%95",
    "snippet": "3 days ago — 年約25歲東南亞女傭周一早上被發現倒斃公園瀑布底，額頭及後腦有創傷。警方昨傍晚拘捕一對從內地返港夫婦，其中持香港身分證的34歲外籍男子涉嫌謀殺，其36歲 ..."
  },
  {
    "index": 176,
    "title": "警拘捕1男1女涉假冒業主中介放租泊車位騙22萬元 - 商業電台",
    "link": "https://www.881903.com/news/local/2554340",
    "snippet": "5 hours ago — 案中1男2女懷疑與多名男子爭執期間被襲擊。 ... 發展局又重申，輸入勞工同樣受香港勞工法例保障，絕不姑息剝削勞工權益事件，已成立跨部門專責小組處理相關事宜 ..."
  },
  {
    "index": 177,
    "title": "[这么过分,一定要发Colg] 跨四来个有500心意点的女角色结婚",
    "link": "https://bbs.colg.cn/thread-9299323-1-1.html?click_from=forum",
    "snippet": "12 hours ago — 为你介绍DNF：如题，更多DNF攻略尽在COLG社区。 - COLG玩家社区- 专业的DNF社区."
  },
  {
    "index": 178,
    "title": "兩度與港姐離婚鬼才男星挺巨腩與性感女合唱索爆靚女身份 ...",
    "link": "https://www.stheadline.com/realtime-entertainment/3396804/%E5%85%A9%E5%BA%A6%E8%88%87%E6%B8%AF%E5%A7%90%E9%9B%A2%E5%A9%9A%E9%AC%BC%E6%89%8D%E7%94%B7%E6%98%9F%E6%8C%BA%E5%B7%A8%E8%85%A9%E8%88%87%E6%80%A7%E6%84%9F%E5%A5%B3%E5%90%88%E5%94%B1-%E7%B4%A2%E7%88%86%E9%9D%9A%E5%A5%B3%E8%BA%AB%E4%BB%BD%E6%9B%9D%E5%85%89",
    "snippet": "2 days ago — 65歲「鬼才」林敏驄百足咁多爪，除為著名填詞人，同時身兼演員、主持及跨媒體創作人，也被譽為香港「無厘頭」始祖。林敏驄首次拍劇集《下流上車族》便 ..."
  },
  {
    "index": 179,
    "title": "橫跨古典與流行的聲樂新女神",
    "link": "https://www.ner.gov.tw/program/657f9dd9210cd20023382d51/672320afd335690022c46f89",
    "snippet": "1 day ago — ... Dynamics**: 動態5. **Legato**: 連奏6. **Timbre**: 音色7. **Soprano**: 女高音8. **Baritone**: 男中音9. **Resonance**: 共振10. **Phrasing**: 措辭."
  },
  {
    "index": 180,
    "title": "中国花滑双人滑新组合挑大梁亚冬会男单冰舞有优势",
    "link": "https://www.chinanews.com.cn/ty/2024/11-01/10312218.shtml",
    "snippet": "5 hours ago — 姚佳说，杨易溪/邓舜阳是通过跨界跨项选拔，从技巧项目选手转项为花样滑冰运动员。 ... 江西网球公开赛：布兹科娃女单女双均晋级“海峡组合”止步次轮. 2024年10 ..."
  },
  {
    "index": 181,
    "title": "电子纸跨入彩屏时代！奥翼创始人兼总经理陈宇",
    "link": "https://news.dayoo.com/finance/202411/01/171077_54740601.htm",
    "snippet": "9 hours ago — ... 男团1/4决赛中发生了令人揪心的一幕。 2024-11-01 14:46. 中国足协信息化 ... 中国女冰以5:0战胜哈萨克斯坦队，收获“开门红”。 2024-10-31 22:50."
  },
  {
    "index": 182,
    "title": "兩男子港鐵打架女乘客反應成焦點網民：港鐵MMA常規賽",
    "link": "https://topick.hket.com/article/3851256/%E6%B8%AF%E9%90%B5MMA%EF%BD%9C%E5%85%A9%E7%94%B7%E5%AD%90%E6%B8%AF%E9%90%B5%E6%89%93%E6%9E%B6%E5%A5%B3%E4%B9%98%E5%AE%A2%E5%8F%8D%E6%87%89%E6%88%90%E7%84%A6%E9%BB%9E%E3%80%80%E7%B6%B2%E6%B0%91%EF%BC%9A%E6%B8%AF%E9%90%B5MMA%E5%B8%B8%E8%A6%8F%E8%B3%BD",
    "snippet": "13 hours ago — 福田口岸MMA丨兩男疑打尖起爭執打架職員勸阻無效禍及途人 · 海底撈MMA｜跨性別女網紅怒毆「香港大律師」 發聲明曝光原因 · 交通事故｜西貢公路MMA 紋身漢 ..."
  },
  {
    "index": 183,
    "title": "變性｜變性手術實際操作會是怎麼做？女變男篇解析！ft.整形 ...",
    "link": "https://www.youtube.com/watch?v=CYRTlKYmzRg"
  },
  {
    "index": 184,
    "title": "数百名“女朋友”被抓、涉案金额近1000万！警方披露详情",
    "link": "https://m.gmw.cn/2024-11/01/content_1303886607.htm",
    "snippet": "12 hours ago — 类似的案件早已不是第一次发生。2021年9月16日，针对“女聊手”专撩男用户要礼物打赏诈骗，广东茂名警方捣毁12个网络交友诈骗窝点31人落网。 除了索要打赏的."
  },
  {
    "index": 185,
    "title": "跨境集團派偽證供宿位打造黑工經濟半年涉款1300萬- 東方日報",
    "link": "https://orientaldaily.on.cc/content/%E8%A6%81%E8%81%9E%E6%B8%AF%E8%81%9E/odn-20241101-1101_00174_001/%E8%B7%A8%E5%A2%83%E9%9B%86%E5%9C%98%E6%B4%BE%E5%81%BD%E8%AD%89%E4%BE%9B%E5%AE%BF%E4%BD%8D--%E6%89%93%E9%80%A0%E9%BB%91%E5%B7%A5%E7%B6%93%E6%BF%9F--%E5%8D%8A%E5%B9%B4%E6%B6%89%E6%AC%BE1300%E8%90%AC-",
    "snippet": "24 hours ago — 入境處高級首席入境事務主任（執法）蘇駿豪表示，在代號「領鋒」行動中，調查員突擊搜查69個目標地點，包括37個住宅和32個工作地點，並拘捕52男45女共 ..."
  },
  {
    "index": 186,
    "title": "《香港跨男: Visibility vs Invisibility》Transgender Men in Hong ...",
    "link": "https://www.youtube.com/watch?v=lyZL4q3R0B4"
  },
  {
    "index": 187,
    "title": "【不一樣又怎樣ep.14】顶级网红天菜！！原来【他】原本是【她 ...",
    "link": "https://www.youtube.com/watch?v=7oX6YnxRD00"
  },
  {
    "index": 188,
    "title": "《自己人2.0》直播 ：跨男跨女跨世代(2024-04-20)",
    "link": "https://www.youtube.com/watch?v=C6yyUh6We3E"
  },
  {
    "index": 189,
    "title": "國內首例未經手術女跨男變更性別判准| 20240531公視手語新聞",
    "link": "https://www.youtube.com/watch?v=72_d5yJcnFs"
  },
  {
    "index": 190,
    "title": "跨性別者第一份工作選擇當軍人！ 回憶頂光頭談退役過程：很 ...",
    "link": "https://m.youtube.com/watch?v=1RNx92urlzY"
  },
  {
    "index": 191,
    "title": "《吾家有男初長成》導演陳冠君",
    "link": "https://www.youtube.com/watch?v=0jD3XLCtakc"
  },
  {
    "index": 192,
    "title": "跨性別系列之三：仔仔 (女跨男) 的故事：成長篇",
    "link": "https://www.youtube.com/watch?v=rRwQUx9Da1A"
  },
  {
    "index": 193,
    "title": "【帥！美！跨性別情侶狂放閃男女互換大方談❤️❤️過程 ...",
    "link": "https://www.youtube.com/watch?v=ukV_6FDjSko"
  },
  {
    "index": 194,
    "title": "跨性別系列之一: Funny (女跨男) 的故事: 成長與手術",
    "link": "https://www.youtube.com/watch?v=RP5isDuXYps"
  },
  {
    "index": 195,
    "title": "「她到他」的跨性別之路，出櫃後得到爸媽暖暖力挺【#誰來晚餐14 ...",
    "link": "https://www.youtube.com/watch?v=UtCjUjDqDCI"
  },
  {
    "index": 196,
    "title": "【女跨男變性獲新生Man爆！他嘆能「站著尿尿」超感動】｜@s_ala",
    "link": "https://www.youtube.com/watch?v=GAxzR9167kQ"
  },
  {
    "index": 197,
    "title": "出現狐臭、毛量爆增！跨性別者分享打男性荷爾蒙變化｜變性 ...",
    "link": "https://m.youtube.com/watch?v=d2_T9p8FMIg"
  },
  {
    "index": 198,
    "title": "拚命賺錢想變女人，卻又花錢做回男人！中國跨性別者李二毛 ...",
    "link": "https://m.youtube.com/watch?v=2gG210QLWdY"
  },
  {
    "index": 199,
    "title": "變性手術實際是怎麼做女變男居然要動到小腿骨？！《VS MEDIA》",
    "link": "https://www.youtube.com/watch?v=1Xfr6Hq8SPI"
  },
  {
    "index": 200,
    "title": "【「從同志到跨性別」成長故事他/她帥顏：叫先生小姐都OK ...",
    "link": "https://www.youtube.com/watch?v=f7OIgNF_eGs"
  },
  {
    "index": 201,
    "title": "跨性別系列之五: Cheryl (女跨男) 的故事：性別與身份",
    "link": "https://www.youtube.com/watch?v=Gp_RnnND5OA"
  },
  {
    "index": 202,
    "title": "跨性別系列之十六：Damien (女跨男) 的故事：愛情篇",
    "link": "https://www.youtube.com/watch?v=gEeIGKT7c9Q"
  },
  {
    "index": 203,
    "title": "變成真正的自己要花多少錢？男跨女從內到外攤開檢視｜VS ...",
    "link": "https://www.youtube.com/watch?v=R552hvj3oU0"
  },
  {
    "index": 204,
    "title": "跨仔話你知第一集| 香港公立醫院性別過渡程序|女跨男|香港跨 ...",
    "link": "https://m.youtube.com/watch?v=21lie5FJnIM"
  },
  {
    "index": 205,
    "title": "跨男HRT 25th week｜用藥半年變化小總結！聲音變低、肌肉 ...",
    "link": "https://www.youtube.com/watch?v=Pjr9NAqBM7o"
  },
  {
    "index": 206,
    "title": "變性｜變性手術實際操作會是怎麼做？男變女篇解析！ft.整形 ...",
    "link": "https://www.youtube.com/watch?v=lvxS_LCitH0"
  },
  {
    "index": 207,
    "title": "跨性別系列之一: Funny (女跨男) 的故事: 工作與愛情",
    "link": "https://www.youtube.com/watch?v=dilwndGtX5k"
  },
  {
    "index": 208,
    "title": "【女跨男手术】再造的阴茎可以选择粗细吗？",
    "link": "https://www.youtube.com/watch?v=ash2qDhGk90"
  },
  {
    "index": 209,
    "title": "跨性別系列之五: Cheryl (女跨男) 的故事：發現與改變",
    "link": "https://www.youtube.com/watch?v=2iIKx-z83Hw"
  },
  {
    "index": 210,
    "title": "那邊太大可以做變性手術嗎? #變性｜VS MEDIAｘ @AllieAllie",
    "link": "https://www.youtube.com/watch?v=0WTn-T9VS6U"
  },
  {
    "index": 211,
    "title": "男跨女變性過程，遠比你想像中的還要猛烈！| 綜口味開房間EP ...",
    "link": "https://www.youtube.com/watch?v=NQjh_BAPwMg"
  },
  {
    "index": 212,
    "title": "跨性别男生慢慢变成女孩子的方法有几种？",
    "link": "https://www.youtube.com/watch?v=vq2P-QU5034"
  },
  {
    "index": 213,
    "title": "《魷魚遊戲》 第 2 季 | 正式前導預告| Netflix",
    "link": "https://www.youtube.com/watch?v=VZeJ-vXDDcA"
  },
  {
    "index": 214,
    "title": "十个勤天上演霸道总裁爱上我大哥无奈演女主| 音乐缘计划花絮 ...",
    "link": "https://www.youtube.com/watch?v=oA2FCr-I6nQ"
  }
]